{
"meta":{"test_sets":[],"test_metrics":[],"learn_metrics":[{"best_value":"Min","name":"MultiClass"}],"launch_mode":"Train","parameters":"","iteration_count":1000,"learn_sets":["learn"],"name":"experiment"},
"iterations":[
{"learn":[3.843192966],"iteration":0,"passed_time":0.1518324267,"remaining_time":151.6805943},
{"learn":[3.444674311],"iteration":1,"passed_time":0.3105252385,"remaining_time":154.952094},
{"learn":[3.2014915],"iteration":2,"passed_time":0.5015357278,"remaining_time":166.6770402},
{"learn":[3.049135216],"iteration":3,"passed_time":0.6744876987,"remaining_time":167.947437},
{"learn":[2.905000816],"iteration":4,"passed_time":0.8491206334,"remaining_time":168.975006},
{"learn":[2.818566616],"iteration":5,"passed_time":1.022811844,"remaining_time":169.4458288},
{"learn":[2.740272084],"iteration":6,"passed_time":1.176461583,"remaining_time":166.8894789},
{"learn":[2.631360854],"iteration":7,"passed_time":1.356088444,"remaining_time":168.1549671},
{"learn":[2.543758838],"iteration":8,"passed_time":1.541154017,"remaining_time":169.6981812},
{"learn":[2.488937072],"iteration":9,"passed_time":1.72273764,"remaining_time":170.5510263},
{"learn":[2.436737105],"iteration":10,"passed_time":1.903951642,"remaining_time":171.1825613},
{"learn":[2.393177117],"iteration":11,"passed_time":2.095037073,"remaining_time":172.4913857},
{"learn":[2.342174711],"iteration":12,"passed_time":2.276423015,"remaining_time":172.8330397},
{"learn":[2.312440515],"iteration":13,"passed_time":2.464648641,"remaining_time":173.5816829},
{"learn":[2.285117797],"iteration":14,"passed_time":2.63582136,"remaining_time":173.0856027},
{"learn":[2.249035281],"iteration":15,"passed_time":2.820356845,"remaining_time":173.451946},
{"learn":[2.221298931],"iteration":16,"passed_time":2.999326003,"remaining_time":173.4316154},
{"learn":[2.192411546],"iteration":17,"passed_time":3.17345337,"remaining_time":173.1295116},
{"learn":[2.163781858],"iteration":18,"passed_time":3.353272926,"remaining_time":173.1347758},
{"learn":[2.141537032],"iteration":19,"passed_time":3.530541965,"remaining_time":172.9965563},
{"learn":[2.107317033],"iteration":20,"passed_time":3.712830995,"remaining_time":173.088645},
{"learn":[2.079615311],"iteration":21,"passed_time":3.900406895,"remaining_time":173.3908156},
{"learn":[2.060775361],"iteration":22,"passed_time":4.077043247,"remaining_time":173.1857066},
{"learn":[2.044024396],"iteration":23,"passed_time":4.263846176,"remaining_time":173.3964112},
{"learn":[2.027188452],"iteration":24,"passed_time":4.44740813,"remaining_time":173.4489171},
{"learn":[2.012631844],"iteration":25,"passed_time":4.63005971,"remaining_time":173.4491599},
{"learn":[1.999327395],"iteration":26,"passed_time":4.810577554,"remaining_time":173.3589615},
{"learn":[1.983235863],"iteration":27,"passed_time":4.994554079,"remaining_time":173.3823773},
{"learn":[1.967593442],"iteration":28,"passed_time":5.16388685,"remaining_time":172.9011769},
{"learn":[1.948412941],"iteration":29,"passed_time":5.353939014,"remaining_time":173.1106948},
{"learn":[1.933952572],"iteration":30,"passed_time":5.530728451,"remaining_time":172.8798667},
{"learn":[1.916958143],"iteration":31,"passed_time":5.69811762,"remaining_time":172.368058},
{"learn":[1.900032759],"iteration":32,"passed_time":5.882101705,"remaining_time":172.3634045},
{"learn":[1.884749585],"iteration":33,"passed_time":6.074038769,"remaining_time":172.5741603},
{"learn":[1.874852987],"iteration":34,"passed_time":6.24603985,"remaining_time":172.2122416},
{"learn":[1.864202417],"iteration":35,"passed_time":6.408293605,"remaining_time":171.5998621},
{"learn":[1.855640831],"iteration":36,"passed_time":6.590470083,"remaining_time":171.530343},
{"learn":[1.842612138],"iteration":37,"passed_time":6.787055868,"remaining_time":171.8196775},
{"learn":[1.83527573],"iteration":38,"passed_time":6.970404637,"remaining_time":171.7579194},
{"learn":[1.825075758],"iteration":39,"passed_time":7.132028995,"remaining_time":171.1686959},
{"learn":[1.807617347],"iteration":40,"passed_time":7.290194313,"remaining_time":170.5194231},
{"learn":[1.79505476],"iteration":41,"passed_time":7.478000499,"remaining_time":170.5696304},
{"learn":[1.786647835],"iteration":42,"passed_time":7.657813324,"remaining_time":170.4308686},
{"learn":[1.77879104],"iteration":43,"passed_time":7.821328152,"remaining_time":169.9361299},
{"learn":[1.76765588],"iteration":44,"passed_time":7.969492078,"remaining_time":169.1303319},
{"learn":[1.76035049],"iteration":45,"passed_time":8.142469564,"remaining_time":168.8677384},
{"learn":[1.754672119],"iteration":46,"passed_time":8.302865721,"remaining_time":168.3538517},
{"learn":[1.74434213],"iteration":47,"passed_time":8.483750065,"remaining_time":168.261043},
{"learn":[1.732865569],"iteration":48,"passed_time":8.6692815,"remaining_time":168.2548308},
{"learn":[1.725769438],"iteration":49,"passed_time":8.833439895,"remaining_time":167.835358},
{"learn":[1.718458524],"iteration":50,"passed_time":8.989313513,"remaining_time":167.2717358},
{"learn":[1.713083845],"iteration":51,"passed_time":9.157090373,"remaining_time":166.9408014},
{"learn":[1.70409726],"iteration":52,"passed_time":9.319510448,"remaining_time":166.5203093},
{"learn":[1.698932904],"iteration":53,"passed_time":9.49097429,"remaining_time":166.2678089},
{"learn":[1.693541441],"iteration":54,"passed_time":9.654980551,"remaining_time":165.8901204},
{"learn":[1.683716332],"iteration":55,"passed_time":9.826220682,"remaining_time":165.6420058},
{"learn":[1.676374825],"iteration":56,"passed_time":9.998834238,"remaining_time":165.4193103},
{"learn":[1.670525966],"iteration":57,"passed_time":10.16363303,"remaining_time":165.0714192},
{"learn":[1.66571034],"iteration":58,"passed_time":10.32075898,"remaining_time":164.6073593},
{"learn":[1.652726684],"iteration":59,"passed_time":10.50070692,"remaining_time":164.5110751},
{"learn":[1.6454692],"iteration":60,"passed_time":10.66274228,"remaining_time":164.1363115},
{"learn":[1.635681693],"iteration":61,"passed_time":10.84678371,"remaining_time":164.1013406},
{"learn":[1.627124038],"iteration":62,"passed_time":11.02994629,"remaining_time":164.0485662},
{"learn":[1.622663091],"iteration":63,"passed_time":11.21067589,"remaining_time":163.9561349},
{"learn":[1.613297608],"iteration":64,"passed_time":11.39485893,"remaining_time":163.9106631},
{"learn":[1.605406397],"iteration":65,"passed_time":11.57108679,"remaining_time":163.74841},
{"learn":[1.598780622],"iteration":66,"passed_time":11.73339466,"remaining_time":163.3918988},
{"learn":[1.593450876],"iteration":67,"passed_time":11.90777501,"remaining_time":163.2065634},
{"learn":[1.585201586],"iteration":68,"passed_time":12.05703628,"remaining_time":162.6826199},
{"learn":[1.579049248],"iteration":69,"passed_time":12.23194056,"remaining_time":162.5100675},
{"learn":[1.57103896],"iteration":70,"passed_time":12.41188715,"remaining_time":162.4034248},
{"learn":[1.565136246],"iteration":71,"passed_time":12.58856594,"remaining_time":162.2526277},
{"learn":[1.559219617],"iteration":72,"passed_time":12.77188123,"remaining_time":162.1853959},
{"learn":[1.555659017],"iteration":73,"passed_time":12.9393785,"remaining_time":161.9170877},
{"learn":[1.55024886],"iteration":74,"passed_time":13.11369155,"remaining_time":161.7355291},
{"learn":[1.545916761],"iteration":75,"passed_time":13.28810702,"remaining_time":161.5554064},
{"learn":[1.541769809],"iteration":76,"passed_time":13.46681037,"remaining_time":161.4268308},
{"learn":[1.536443675],"iteration":77,"passed_time":13.63044298,"remaining_time":161.118826},
{"learn":[1.532353765],"iteration":78,"passed_time":13.78850056,"remaining_time":160.7494813},
{"learn":[1.530093124],"iteration":79,"passed_time":13.94273091,"remaining_time":160.3414054},
{"learn":[1.527105173],"iteration":80,"passed_time":14.10577714,"remaining_time":160.0396196},
{"learn":[1.52352046],"iteration":81,"passed_time":14.29678654,"remaining_time":160.0542688},
{"learn":[1.516736413],"iteration":82,"passed_time":14.46517694,"remaining_time":159.8140633},
{"learn":[1.513920437],"iteration":83,"passed_time":14.62225495,"remaining_time":159.4522087},
{"learn":[1.509782196],"iteration":84,"passed_time":14.79591834,"remaining_time":159.2737092},
{"learn":[1.506692377],"iteration":85,"passed_time":14.9544046,"remaining_time":158.934021},
{"learn":[1.50185848],"iteration":86,"passed_time":15.1066206,"remaining_time":158.5326966},
{"learn":[1.496839543],"iteration":87,"passed_time":15.29003253,"remaining_time":158.4603371},
{"learn":[1.493691301],"iteration":88,"passed_time":15.46580933,"remaining_time":158.3073292},
{"learn":[1.488374514],"iteration":89,"passed_time":15.63531097,"remaining_time":158.0903664},
{"learn":[1.484862989],"iteration":90,"passed_time":15.79437928,"remaining_time":157.7702282},
{"learn":[1.482659602],"iteration":91,"passed_time":15.95777417,"remaining_time":157.4962929},
{"learn":[1.478131522],"iteration":92,"passed_time":16.11790792,"remaining_time":157.1929299},
{"learn":[1.471638632],"iteration":93,"passed_time":16.28989316,"remaining_time":157.0068426},
{"learn":[1.46688674],"iteration":94,"passed_time":16.46460593,"remaining_time":156.8470354},
{"learn":[1.463017455],"iteration":95,"passed_time":16.6568975,"remaining_time":156.8524514},
{"learn":[1.460132753],"iteration":96,"passed_time":16.83594946,"remaining_time":156.7305398},
{"learn":[1.455406567],"iteration":97,"passed_time":17.01577395,"remaining_time":156.6145725},
{"learn":[1.450333668],"iteration":98,"passed_time":17.19266418,"remaining_time":156.4706104},
{"learn":[1.447866636],"iteration":99,"passed_time":17.35394945,"remaining_time":156.1855451},
{"learn":[1.444824936],"iteration":100,"passed_time":17.55433072,"remaining_time":156.250924},
{"learn":[1.441481456],"iteration":101,"passed_time":17.73472669,"remaining_time":156.1351429},
{"learn":[1.439249708],"iteration":102,"passed_time":17.91923774,"remaining_time":156.0539442},
{"learn":[1.434971146],"iteration":103,"passed_time":18.09215637,"remaining_time":155.8708856},
{"learn":[1.431765756],"iteration":104,"passed_time":18.25764736,"remaining_time":155.6247085},
{"learn":[1.429852146],"iteration":105,"passed_time":18.41377276,"remaining_time":155.3010646},
{"learn":[1.427746591],"iteration":106,"passed_time":18.56804246,"remaining_time":154.9650647},
{"learn":[1.423519334],"iteration":107,"passed_time":18.75353556,"remaining_time":154.8903122},
{"learn":[1.418124792],"iteration":108,"passed_time":18.9183209,"remaining_time":154.6442562},
{"learn":[1.41307983],"iteration":109,"passed_time":19.09725406,"remaining_time":154.5141465},
{"learn":[1.41143284],"iteration":110,"passed_time":19.26615796,"remaining_time":154.3028327},
{"learn":[1.4053607],"iteration":111,"passed_time":19.43859701,"remaining_time":154.1203049},
{"learn":[1.402603359],"iteration":112,"passed_time":19.61968961,"remaining_time":154.0058822},
{"learn":[1.399029375],"iteration":113,"passed_time":19.79918594,"remaining_time":153.8778837},
{"learn":[1.395363402],"iteration":114,"passed_time":19.98666143,"remaining_time":153.8103945},
{"learn":[1.393503116],"iteration":115,"passed_time":20.15481022,"remaining_time":153.5935537},
{"learn":[1.391142732],"iteration":116,"passed_time":20.31051642,"remaining_time":153.283641},
{"learn":[1.387917053],"iteration":117,"passed_time":20.47948387,"remaining_time":153.0754642},
{"learn":[1.386454785],"iteration":118,"passed_time":20.63911833,"remaining_time":152.7988509},
{"learn":[1.384392994],"iteration":119,"passed_time":20.80733472,"remaining_time":152.5871213},
{"learn":[1.382478853],"iteration":120,"passed_time":20.9695174,"remaining_time":152.3322793},
{"learn":[1.379974005],"iteration":121,"passed_time":21.15049207,"remaining_time":152.2141971},
{"learn":[1.377782409],"iteration":122,"passed_time":21.31648498,"remaining_time":151.988271},
{"learn":[1.373560995],"iteration":123,"passed_time":21.49455922,"remaining_time":151.8486603},
{"learn":[1.371343374],"iteration":124,"passed_time":21.6768902,"remaining_time":151.7382314},
{"learn":[1.368555123],"iteration":125,"passed_time":21.87056425,"remaining_time":151.7053425},
{"learn":[1.36595648],"iteration":126,"passed_time":22.05429043,"remaining_time":151.6015397},
{"learn":[1.362970654],"iteration":127,"passed_time":22.24502701,"remaining_time":151.5442465},
{"learn":[1.361033887],"iteration":128,"passed_time":22.46689934,"remaining_time":151.6951111},
{"learn":[1.359437884],"iteration":129,"passed_time":22.64896517,"remaining_time":151.5738438},
{"learn":[1.35806973],"iteration":130,"passed_time":22.82359077,"remaining_time":151.4022929},
{"learn":[1.354998181],"iteration":131,"passed_time":23.03886145,"remaining_time":151.4979677},
{"learn":[1.352305],"iteration":132,"passed_time":23.2178609,"remaining_time":151.3525218},
{"learn":[1.34958505],"iteration":133,"passed_time":23.37508293,"remaining_time":151.0658344},
{"learn":[1.348834902],"iteration":134,"passed_time":23.52130703,"remaining_time":150.7105969},
{"learn":[1.345650226],"iteration":135,"passed_time":23.69540991,"remaining_time":150.5355453},
{"learn":[1.343013236],"iteration":136,"passed_time":23.85612908,"remaining_time":150.2761999},
{"learn":[1.341461316],"iteration":137,"passed_time":24.02238534,"remaining_time":150.0528708},
{"learn":[1.341091235],"iteration":138,"passed_time":24.19254032,"remaining_time":149.8545124},
{"learn":[1.339144802],"iteration":139,"passed_time":24.38550839,"remaining_time":149.7966944},
{"learn":[1.334777862],"iteration":140,"passed_time":24.57211645,"remaining_time":149.698213},
{"learn":[1.332879654],"iteration":141,"passed_time":24.74095981,"remaining_time":149.4911515},
{"learn":[1.332145015],"iteration":142,"passed_time":24.89885033,"remaining_time":149.2189841},
{"learn":[1.329195623],"iteration":143,"passed_time":25.05080081,"remaining_time":148.9130937},
{"learn":[1.327239949],"iteration":144,"passed_time":25.22224004,"remaining_time":148.724243},
{"learn":[1.324539119],"iteration":145,"passed_time":25.39930481,"remaining_time":148.5685364},
{"learn":[1.322651321],"iteration":146,"passed_time":25.5511082,"remaining_time":148.2659544},
{"learn":[1.320931993],"iteration":147,"passed_time":25.70938042,"remaining_time":148.0026495},
{"learn":[1.318246354],"iteration":148,"passed_time":25.88916843,"remaining_time":147.8636398},
{"learn":[1.314572945],"iteration":149,"passed_time":26.0520898,"remaining_time":147.6285089},
{"learn":[1.311851295],"iteration":150,"passed_time":26.23702506,"remaining_time":147.5181078},
{"learn":[1.309098522],"iteration":151,"passed_time":26.4128222,"remaining_time":147.3557449},
{"learn":[1.308771992],"iteration":152,"passed_time":26.55402064,"remaining_time":147.0016698},
{"learn":[1.303914302],"iteration":153,"passed_time":26.72700145,"remaining_time":146.824956},
{"learn":[1.301294202],"iteration":154,"passed_time":26.89768053,"remaining_time":146.6357423},
{"learn":[1.298265249],"iteration":155,"passed_time":27.07915455,"remaining_time":146.5051695},
{"learn":[1.2980374],"iteration":156,"passed_time":27.219931,"remaining_time":146.1554257},
{"learn":[1.29495661],"iteration":157,"passed_time":27.38390646,"remaining_time":145.9319572},
{"learn":[1.292999342],"iteration":158,"passed_time":27.54322914,"remaining_time":145.6846271},
{"learn":[1.289512461],"iteration":159,"passed_time":27.73980234,"remaining_time":145.6339623},
{"learn":[1.287569427],"iteration":160,"passed_time":27.91400198,"remaining_time":145.4648923},
{"learn":[1.285006475],"iteration":161,"passed_time":28.11516568,"remaining_time":145.4352398},
{"learn":[1.282068874],"iteration":162,"passed_time":28.28069863,"remaining_time":145.2205199},
{"learn":[1.28081576],"iteration":163,"passed_time":28.43996752,"remaining_time":144.9744686},
{"learn":[1.279864425],"iteration":164,"passed_time":28.58679295,"remaining_time":144.6664977},
{"learn":[1.278651888],"iteration":165,"passed_time":28.74049373,"remaining_time":144.3950106},
{"learn":[1.275045506],"iteration":166,"passed_time":28.92873004,"remaining_time":144.2971983},
{"learn":[1.274404662],"iteration":167,"passed_time":29.07431515,"remaining_time":143.9870846},
{"learn":[1.271996902],"iteration":168,"passed_time":29.23484509,"remaining_time":143.752404},
{"learn":[1.271241336],"iteration":169,"passed_time":29.37405897,"remaining_time":143.4145232},
{"learn":[1.269937341],"iteration":170,"passed_time":29.52284556,"remaining_time":143.1253741},
{"learn":[1.268836338],"iteration":171,"passed_time":29.68496508,"remaining_time":142.9020412},
{"learn":[1.267211549],"iteration":172,"passed_time":29.8570919,"remaining_time":142.7272543},
{"learn":[1.264498291],"iteration":173,"passed_time":30.03837012,"remaining_time":142.5959409},
{"learn":[1.263123232],"iteration":174,"passed_time":30.19589435,"remaining_time":142.3520734},
{"learn":[1.262408882],"iteration":175,"passed_time":30.34345249,"remaining_time":142.0625276},
{"learn":[1.261941925],"iteration":176,"passed_time":30.49531448,"remaining_time":141.7945978},
{"learn":[1.259171625],"iteration":177,"passed_time":30.66848339,"remaining_time":141.6263671},
{"learn":[1.256528475],"iteration":178,"passed_time":30.81417654,"remaining_time":141.3320611},
{"learn":[1.254744457],"iteration":179,"passed_time":30.9725219,"remaining_time":141.0970442},
{"learn":[1.254139622],"iteration":180,"passed_time":31.11251808,"remaining_time":140.779847},
{"learn":[1.251150397],"iteration":181,"passed_time":31.2855034,"remaining_time":140.6128669},
{"learn":[1.248355878],"iteration":182,"passed_time":31.44413588,"remaining_time":140.3817432},
{"learn":[1.245716658],"iteration":183,"passed_time":31.60713424,"remaining_time":140.1707693},
{"learn":[1.244004022],"iteration":184,"passed_time":31.77051176,"remaining_time":139.9619842},
{"learn":[1.241826129],"iteration":185,"passed_time":31.9501599,"remaining_time":139.8248933},
{"learn":[1.241507566],"iteration":186,"passed_time":32.10058381,"remaining_time":139.5602922},
{"learn":[1.238254057],"iteration":187,"passed_time":32.26255824,"remaining_time":139.3467941},
{"learn":[1.237179397],"iteration":188,"passed_time":32.41556893,"remaining_time":139.0953778},
{"learn":[1.236682379],"iteration":189,"passed_time":32.56635008,"remaining_time":138.8354924},
{"learn":[1.235619829],"iteration":190,"passed_time":32.71797731,"remaining_time":138.5803332},
{"learn":[1.235134177],"iteration":191,"passed_time":32.86121854,"remaining_time":138.2909614},
{"learn":[1.233039031],"iteration":192,"passed_time":33.04195157,"remaining_time":138.15987},
{"learn":[1.232351555],"iteration":193,"passed_time":33.18680019,"remaining_time":137.8791802},
{"learn":[1.230584533],"iteration":194,"passed_time":33.34502096,"remaining_time":137.6550865},
{"learn":[1.22884258],"iteration":195,"passed_time":33.53668172,"remaining_time":137.5688372},
{"learn":[1.228036452],"iteration":196,"passed_time":33.68357132,"remaining_time":137.2990242},
{"learn":[1.22741919],"iteration":197,"passed_time":33.82611064,"remaining_time":137.012832},
{"learn":[1.226083434],"iteration":198,"passed_time":33.97928098,"remaining_time":136.7708747},
{"learn":[1.224445579],"iteration":199,"passed_time":34.1481845,"remaining_time":136.592738},
{"learn":[1.223095908],"iteration":200,"passed_time":34.30611974,"remaining_time":136.3710929},
{"learn":[1.221856602],"iteration":201,"passed_time":34.45834405,"remaining_time":136.1275176},
{"learn":[1.220986103],"iteration":202,"passed_time":34.60617721,"remaining_time":135.8676021},
{"learn":[1.220575657],"iteration":203,"passed_time":34.74838017,"remaining_time":135.5868168},
{"learn":[1.2184547],"iteration":204,"passed_time":34.92378726,"remaining_time":135.4361506},
{"learn":[1.215931156],"iteration":205,"passed_time":35.10478668,"remaining_time":135.3067992},
{"learn":[1.215049079],"iteration":206,"passed_time":35.25792764,"remaining_time":135.0702252},
{"learn":[1.213911748],"iteration":207,"passed_time":35.41647144,"remaining_time":134.8550259},
{"learn":[1.212760183],"iteration":208,"passed_time":35.57547438,"remaining_time":134.6421064},
{"learn":[1.211775176],"iteration":209,"passed_time":35.71922728,"remaining_time":134.3723312},
{"learn":[1.210864737],"iteration":210,"passed_time":35.87552972,"remaining_time":134.1506775},
{"learn":[1.208950808],"iteration":211,"passed_time":36.05680422,"remaining_time":134.022461},
{"learn":[1.207102844],"iteration":212,"passed_time":36.22072978,"remaining_time":133.8296448},
{"learn":[1.206757725],"iteration":213,"passed_time":36.36622558,"remaining_time":133.569408},
{"learn":[1.206593292],"iteration":214,"passed_time":36.50277492,"remaining_time":133.2775735},
{"learn":[1.205791413],"iteration":215,"passed_time":36.65810807,"remaining_time":133.0553552},
{"learn":[1.203444307],"iteration":216,"passed_time":36.82211664,"remaining_time":132.8650568},
{"learn":[1.203081236],"iteration":217,"passed_time":36.96900284,"remaining_time":132.613579},
{"learn":[1.202407781],"iteration":218,"passed_time":37.11396821,"remaining_time":132.3562063},
{"learn":[1.201916287],"iteration":219,"passed_time":37.25617142,"remaining_time":132.0900623},
{"learn":[1.200637997],"iteration":220,"passed_time":37.41218458,"remaining_time":131.8737185},
{"learn":[1.199941386],"iteration":221,"passed_time":37.56854271,"remaining_time":131.6591272},
{"learn":[1.198489847],"iteration":222,"passed_time":37.73666276,"remaining_time":131.4860402},
{"learn":[1.196984771],"iteration":223,"passed_time":37.92655689,"remaining_time":131.3884292},
{"learn":[1.196387903],"iteration":224,"passed_time":38.08360226,"remaining_time":131.1768522},
{"learn":[1.195375703],"iteration":225,"passed_time":38.23266672,"remaining_time":130.9384249},
{"learn":[1.194612171],"iteration":226,"passed_time":38.39240418,"remaining_time":130.7371296},
{"learn":[1.19279703],"iteration":227,"passed_time":38.53601584,"remaining_time":130.4815975},
{"learn":[1.190915499],"iteration":228,"passed_time":38.71036174,"remaining_time":130.3305192},
{"learn":[1.190416038],"iteration":229,"passed_time":38.8605255,"remaining_time":130.098281},
{"learn":[1.189298252],"iteration":230,"passed_time":39.01835113,"remaining_time":129.8922598},
{"learn":[1.188403853],"iteration":231,"passed_time":39.1782105,"remaining_time":129.6933865},
{"learn":[1.18664501],"iteration":232,"passed_time":39.3556111,"remaining_time":129.552591},
{"learn":[1.184876926],"iteration":233,"passed_time":39.52522837,"remaining_time":129.386004},
{"learn":[1.183184791],"iteration":234,"passed_time":39.69282136,"remaining_time":129.2128014},
{"learn":[1.181429241],"iteration":235,"passed_time":39.87334312,"remaining_time":129.0815006},
{"learn":[1.180333124],"iteration":236,"passed_time":40.0294802,"remaining_time":128.8712801},
{"learn":[1.178703661],"iteration":237,"passed_time":40.19647666,"remaining_time":128.6962824},
{"learn":[1.177481776],"iteration":238,"passed_time":40.35279488,"remaining_time":128.4873511},
{"learn":[1.17672876],"iteration":239,"passed_time":40.4955734,"remaining_time":128.2359824},
{"learn":[1.176026838],"iteration":240,"passed_time":40.647092,"remaining_time":128.0130408},
{"learn":[1.173953575],"iteration":241,"passed_time":40.82001415,"remaining_time":127.8577303},
{"learn":[1.173123334],"iteration":242,"passed_time":41.01965705,"remaining_time":127.785516},
{"learn":[1.172420137],"iteration":243,"passed_time":41.17482868,"remaining_time":127.5744692},
{"learn":[1.17207948],"iteration":244,"passed_time":41.33797324,"remaining_time":127.3884481},
{"learn":[1.171971982],"iteration":245,"passed_time":41.51316621,"remaining_time":127.239542},
{"learn":[1.171626225],"iteration":246,"passed_time":41.68146477,"remaining_time":127.0694048},
{"learn":[1.169875349],"iteration":247,"passed_time":41.86565641,"remaining_time":126.9474743},
{"learn":[1.169146446],"iteration":248,"passed_time":42.02382953,"remaining_time":126.7465702},
{"learn":[1.168331183],"iteration":249,"passed_time":42.17902831,"remaining_time":126.5370849},
{"learn":[1.167141803],"iteration":250,"passed_time":42.33608078,"remaining_time":126.3335638},
{"learn":[1.166017325],"iteration":251,"passed_time":42.50455857,"remaining_time":126.1643247},
{"learn":[1.164434918],"iteration":252,"passed_time":42.65392187,"remaining_time":125.9386547},
{"learn":[1.164306176],"iteration":253,"passed_time":42.78775484,"remaining_time":125.6679729},
{"learn":[1.163390851],"iteration":254,"passed_time":42.93481568,"remaining_time":125.4370105},
{"learn":[1.162779643],"iteration":255,"passed_time":43.12733505,"remaining_time":125.3388175},
{"learn":[1.161440488],"iteration":256,"passed_time":43.30165757,"remaining_time":125.1872824},
{"learn":[1.160456543],"iteration":257,"passed_time":43.46970648,"remaining_time":125.0175279},
{"learn":[1.159447317],"iteration":258,"passed_time":43.65541038,"remaining_time":124.8982976},
{"learn":[1.158539003],"iteration":259,"passed_time":43.82838854,"remaining_time":124.7423366},
{"learn":[1.158284173],"iteration":260,"passed_time":43.97750176,"remaining_time":124.5186736},
{"learn":[1.157537743],"iteration":261,"passed_time":44.12437314,"remaining_time":124.2892648},
{"learn":[1.156414327],"iteration":262,"passed_time":44.28401766,"remaining_time":124.0962776},
{"learn":[1.154467682],"iteration":263,"passed_time":44.46439647,"remaining_time":123.9613477},
{"learn":[1.153431581],"iteration":264,"passed_time":44.60641034,"remaining_time":123.7196664},
{"learn":[1.151863834],"iteration":265,"passed_time":44.79865224,"remaining_time":123.6173336},
{"learn":[1.151324433],"iteration":266,"passed_time":44.96455934,"remaining_time":123.4420299},
{"learn":[1.14999675],"iteration":267,"passed_time":45.11493105,"remaining_time":123.2243639},
{"learn":[1.148101835],"iteration":268,"passed_time":45.29282538,"remaining_time":123.0819901},
{"learn":[1.145026675],"iteration":269,"passed_time":45.48745467,"remaining_time":122.9845997},
{"learn":[1.144643209],"iteration":270,"passed_time":45.65627748,"remaining_time":122.8170712},
{"learn":[1.142826581],"iteration":271,"passed_time":45.88202311,"remaining_time":122.8018854},
{"learn":[1.142476894],"iteration":272,"passed_time":46.09549055,"remaining_time":122.7524602},
{"learn":[1.141629234],"iteration":273,"passed_time":46.27857149,"remaining_time":122.6213245},
{"learn":[1.140225707],"iteration":274,"passed_time":46.4906852,"remaining_time":122.5663519},
{"learn":[1.139562769],"iteration":275,"passed_time":46.69106253,"remaining_time":122.4794539},
{"learn":[1.137905794],"iteration":276,"passed_time":46.92208111,"remaining_time":122.4717135},
{"learn":[1.136589052],"iteration":277,"passed_time":47.0780846,"remaining_time":122.2675435},
{"learn":[1.13542134],"iteration":278,"passed_time":47.24734147,"remaining_time":122.0979685},
{"learn":[1.132144144],"iteration":279,"passed_time":47.42981269,"remaining_time":121.9623755},
{"learn":[1.12963271],"iteration":280,"passed_time":47.59527181,"remaining_time":121.7829197},
{"learn":[1.129116678],"iteration":281,"passed_time":47.74721238,"remaining_time":121.5691436},
{"learn":[1.127881409],"iteration":282,"passed_time":47.90670077,"remaining_time":121.3749274},
{"learn":[1.126375484],"iteration":283,"passed_time":48.09365727,"remaining_time":121.2502064},
{"learn":[1.125689176],"iteration":284,"passed_time":48.27251611,"remaining_time":121.1047334},
{"learn":[1.123625048],"iteration":285,"passed_time":48.45500671,"remaining_time":120.9680937},
{"learn":[1.122026283],"iteration":286,"passed_time":48.61337218,"remaining_time":120.7711999},
{"learn":[1.121763274],"iteration":287,"passed_time":48.76030158,"remaining_time":120.5463011},
{"learn":[1.120483604],"iteration":288,"passed_time":48.91907402,"remaining_time":120.3510783},
{"learn":[1.119286469],"iteration":289,"passed_time":49.06380324,"remaining_time":120.1217252},
{"learn":[1.118992019],"iteration":290,"passed_time":49.20354577,"remaining_time":119.880804},
{"learn":[1.11873464],"iteration":291,"passed_time":49.34120887,"remaining_time":119.6355338},
{"learn":[1.117682819],"iteration":292,"passed_time":49.495772,"remaining_time":119.4317775},
{"learn":[1.117017118],"iteration":293,"passed_time":49.64344063,"remaining_time":119.2117996},
{"learn":[1.116487171],"iteration":294,"passed_time":49.78277683,"remaining_time":118.9723989},
{"learn":[1.11623744],"iteration":295,"passed_time":49.96057462,"remaining_time":118.8251504},
{"learn":[1.115526701],"iteration":296,"passed_time":50.1143985,"remaining_time":118.62095},
{"learn":[1.115294072],"iteration":297,"passed_time":50.25439785,"remaining_time":118.3845211},
{"learn":[1.114711332],"iteration":298,"passed_time":50.40510577,"remaining_time":118.1738433},
{"learn":[1.113779861],"iteration":299,"passed_time":50.56989921,"remaining_time":117.9964315},
{"learn":[1.111682804],"iteration":300,"passed_time":50.7519819,"remaining_time":117.8592536},
{"learn":[1.110383376],"iteration":301,"passed_time":50.92671857,"remaining_time":117.7047999},
{"learn":[1.11014448],"iteration":302,"passed_time":51.07168148,"remaining_time":117.4817228},
{"learn":[1.109202387],"iteration":303,"passed_time":51.22776017,"remaining_time":117.2846088},
{"learn":[1.108317867],"iteration":304,"passed_time":51.36959139,"remaining_time":117.0552984},
{"learn":[1.107329992],"iteration":305,"passed_time":51.52179505,"remaining_time":116.8500842},
{"learn":[1.105797086],"iteration":306,"passed_time":51.68770718,"remaining_time":116.6761599},
{"learn":[1.105065633],"iteration":307,"passed_time":51.84717619,"remaining_time":116.4878114},
{"learn":[1.10438145],"iteration":308,"passed_time":52.00014678,"remaining_time":116.2851179},
{"learn":[1.103311783],"iteration":309,"passed_time":52.16669106,"remaining_time":116.1129575},
{"learn":[1.101484107],"iteration":310,"passed_time":52.34302177,"remaining_time":115.9625145},
{"learn":[1.099917422],"iteration":311,"passed_time":52.51174477,"remaining_time":115.7951295},
{"learn":[1.099490618],"iteration":312,"passed_time":52.66540113,"remaining_time":115.5946664},
{"learn":[1.098890244],"iteration":313,"passed_time":52.81008004,"remaining_time":115.3748882},
{"learn":[1.096819955],"iteration":314,"passed_time":52.97233286,"remaining_time":115.1938032},
{"learn":[1.095896026],"iteration":315,"passed_time":53.1313517,"remaining_time":115.0058372},
{"learn":[1.095315835],"iteration":316,"passed_time":53.29175115,"remaining_time":114.8210285},
{"learn":[1.094603503],"iteration":317,"passed_time":53.45175799,"remaining_time":114.6355313},
{"learn":[1.094146106],"iteration":318,"passed_time":53.60302091,"remaining_time":114.4315274},
{"learn":[1.093034481],"iteration":319,"passed_time":53.7663412,"remaining_time":114.2534751},
{"learn":[1.092483608],"iteration":320,"passed_time":53.92468964,"remaining_time":114.0649977},
{"learn":[1.092059565],"iteration":321,"passed_time":54.07335255,"remaining_time":113.8563138},
{"learn":[1.090681851],"iteration":322,"passed_time":54.24032148,"remaining_time":113.6863704},
{"learn":[1.089052388],"iteration":323,"passed_time":54.4042177,"remaining_time":113.5100345},
{"learn":[1.087902416],"iteration":324,"passed_time":54.56262186,"remaining_time":113.3223685},
{"learn":[1.087506097],"iteration":325,"passed_time":54.70567142,"remaining_time":113.1031366},
{"learn":[1.086505794],"iteration":326,"passed_time":54.8595217,"remaining_time":112.9065997},
{"learn":[1.085370268],"iteration":327,"passed_time":55.02719066,"remaining_time":112.7386345},
{"learn":[1.084174621],"iteration":328,"passed_time":55.17208217,"remaining_time":112.5242162},
{"learn":[1.082678255],"iteration":329,"passed_time":55.33977789,"remaining_time":112.3565188},
{"learn":[1.080503761],"iteration":330,"passed_time":55.51237664,"remaining_time":112.198731},
{"learn":[1.080064528],"iteration":331,"passed_time":55.65974474,"remaining_time":111.9900888},
{"learn":[1.079774327],"iteration":332,"passed_time":55.80083222,"remaining_time":111.7692345},
{"learn":[1.079269023],"iteration":333,"passed_time":55.95000375,"remaining_time":111.5649775},
{"learn":[1.078619575],"iteration":334,"passed_time":56.10443371,"remaining_time":111.3714878},
{"learn":[1.078386628],"iteration":335,"passed_time":56.2556365,"remaining_time":111.1718531},
{"learn":[1.077229539],"iteration":336,"passed_time":56.40827896,"remaining_time":110.9753381},
{"learn":[1.076809957],"iteration":337,"passed_time":56.56560725,"remaining_time":110.7882604},
{"learn":[1.075858623],"iteration":338,"passed_time":56.73050867,"remaining_time":110.6161246},
{"learn":[1.07518145],"iteration":339,"passed_time":56.88925752,"remaining_time":110.4320881},
{"learn":[1.074477616],"iteration":340,"passed_time":57.09085625,"remaining_time":110.3310096},
{"learn":[1.073613491],"iteration":341,"passed_time":57.24522565,"remaining_time":110.1384751},
{"learn":[1.07125385],"iteration":342,"passed_time":57.42458583,"remaining_time":109.9940318},
{"learn":[1.070146792],"iteration":343,"passed_time":57.58344739,"remaining_time":109.810295},
{"learn":[1.06849789],"iteration":344,"passed_time":57.74411506,"remaining_time":109.6301315},
{"learn":[1.06780096],"iteration":345,"passed_time":57.89886664,"remaining_time":109.4388982},
{"learn":[1.066659592],"iteration":346,"passed_time":58.08349711,"remaining_time":109.3041026},
{"learn":[1.065836681],"iteration":347,"passed_time":58.23495437,"remaining_time":109.1068685},
{"learn":[1.064369209],"iteration":348,"passed_time":58.39987118,"remaining_time":108.9350033},
{"learn":[1.062232211],"iteration":349,"passed_time":58.59175682,"remaining_time":108.8132627},
{"learn":[1.061611656],"iteration":350,"passed_time":58.78478361,"remaining_time":108.6932324},
{"learn":[1.060521913],"iteration":351,"passed_time":58.92480119,"remaining_time":108.4752022},
{"learn":[1.058780809],"iteration":352,"passed_time":59.10112115,"remaining_time":108.3241512},
{"learn":[1.058165246],"iteration":353,"passed_time":59.27604742,"remaining_time":108.1704142},
{"learn":[1.057151877],"iteration":354,"passed_time":59.46110697,"remaining_time":108.034969},
{"learn":[1.056140102],"iteration":355,"passed_time":59.62619718,"remaining_time":107.8631207},
{"learn":[1.055294034],"iteration":356,"passed_time":59.77881671,"remaining_time":107.6688491},
{"learn":[1.054023499],"iteration":357,"passed_time":59.97029708,"remaining_time":107.5444992},
{"learn":[1.053201544],"iteration":358,"passed_time":60.12619609,"remaining_time":107.3562443},
{"learn":[1.052783663],"iteration":359,"passed_time":60.27860831,"remaining_time":107.1619703},
{"learn":[1.051804073],"iteration":360,"passed_time":60.44461451,"remaining_time":106.9919908},
{"learn":[1.050815241],"iteration":361,"passed_time":60.61151032,"remaining_time":106.8236011},
{"learn":[1.049869431],"iteration":362,"passed_time":60.76958615,"remaining_time":106.6397421},
{"learn":[1.048584555],"iteration":363,"passed_time":60.94298445,"remaining_time":106.482797},
{"learn":[1.047719899],"iteration":364,"passed_time":61.12928944,"remaining_time":106.3482159},
{"learn":[1.045890736],"iteration":365,"passed_time":61.29144645,"remaining_time":106.171522},
{"learn":[1.044759566],"iteration":366,"passed_time":61.47740089,"remaining_time":106.035953},
{"learn":[1.04403778],"iteration":367,"passed_time":61.67215219,"remaining_time":105.9152179},
{"learn":[1.043571141],"iteration":368,"passed_time":61.83204856,"remaining_time":105.7344787},
{"learn":[1.043361776],"iteration":369,"passed_time":61.98784903,"remaining_time":105.5468781},
{"learn":[1.04271084],"iteration":370,"passed_time":62.14324156,"remaining_time":105.3587572},
{"learn":[1.042060223],"iteration":371,"passed_time":62.29430804,"remaining_time":105.1635093},
{"learn":[1.04135692],"iteration":372,"passed_time":62.46634385,"remaining_time":105.0037469},
{"learn":[1.040774286],"iteration":373,"passed_time":62.6207467,"remaining_time":104.8144049},
{"learn":[1.040125475],"iteration":374,"passed_time":62.77071624,"remaining_time":104.6178604},
{"learn":[1.039884348],"iteration":375,"passed_time":62.92431802,"remaining_time":104.4275916},
{"learn":[1.039366086],"iteration":376,"passed_time":63.07694719,"remaining_time":104.2359101},
{"learn":[1.038790463],"iteration":377,"passed_time":63.23620689,"remaining_time":104.0553457},
{"learn":[1.037121166],"iteration":378,"passed_time":63.43634787,"remaining_time":103.9418787},
{"learn":[1.036200955],"iteration":379,"passed_time":63.60901436,"remaining_time":103.7831287},
{"learn":[1.034435845],"iteration":380,"passed_time":63.78258072,"remaining_time":103.6257676},
{"learn":[1.034216706],"iteration":381,"passed_time":63.93207063,"remaining_time":103.4293708},
{"learn":[1.033825168],"iteration":382,"passed_time":64.08026835,"remaining_time":103.2311373},
{"learn":[1.033302019],"iteration":383,"passed_time":64.23263087,"remaining_time":103.0398453},
{"learn":[1.032741267],"iteration":384,"passed_time":64.40268252,"remaining_time":102.8770123},
{"learn":[1.031549868],"iteration":385,"passed_time":64.56462933,"remaining_time":102.7012498},
{"learn":[1.03108238],"iteration":386,"passed_time":64.72197195,"remaining_time":102.5182656},
{"learn":[1.030642828],"iteration":387,"passed_time":64.88777937,"remaining_time":102.3487654},
{"learn":[1.029635833],"iteration":388,"passed_time":65.05292256,"remaining_time":102.1782408},
{"learn":[1.029156236],"iteration":389,"passed_time":65.21431231,"remaining_time":102.0018731},
{"learn":[1.028257906],"iteration":390,"passed_time":65.37893623,"remaining_time":101.8306193},
{"learn":[1.02728469],"iteration":391,"passed_time":65.56497863,"remaining_time":101.6926199},
{"learn":[1.026800737],"iteration":392,"passed_time":65.74813875,"remaining_time":101.5499242},
{"learn":[1.026269303],"iteration":393,"passed_time":65.9324317,"remaining_time":101.4087655},
{"learn":[1.025696654],"iteration":394,"passed_time":66.0831986,"remaining_time":101.2160384},
{"learn":[1.025321899],"iteration":395,"passed_time":66.22953538,"remaining_time":101.0167661},
{"learn":[1.024443646],"iteration":396,"passed_time":66.39497263,"remaining_time":100.846772},
{"learn":[1.023987736],"iteration":397,"passed_time":66.53641021,"remaining_time":100.6404999},
{"learn":[1.023624134],"iteration":398,"passed_time":66.6805426,"remaining_time":100.4386118},
{"learn":[1.023257239],"iteration":399,"passed_time":66.83384985,"remaining_time":100.2507748},
{"learn":[1.022263734],"iteration":400,"passed_time":66.98967347,"remaining_time":100.0668688},
{"learn":[1.022109286],"iteration":401,"passed_time":67.13918394,"remaining_time":99.87371143},
{"learn":[1.021736549],"iteration":402,"passed_time":67.29538999,"remaining_time":99.69068939},
{"learn":[1.02150477],"iteration":403,"passed_time":67.47165799,"remaining_time":99.53739644},
{"learn":[1.020515089],"iteration":404,"passed_time":67.65686555,"remaining_time":99.39712346},
{"learn":[1.020182504],"iteration":405,"passed_time":67.81342608,"remaining_time":99.21471698},
{"learn":[1.019672102],"iteration":406,"passed_time":67.98685475,"remaining_time":99.05701442},
{"learn":[1.01915352],"iteration":407,"passed_time":68.13948175,"remaining_time":98.86905196},
{"learn":[1.018135372],"iteration":408,"passed_time":68.32413874,"remaining_time":98.72754522},
{"learn":[1.01616079],"iteration":409,"passed_time":68.50300336,"remaining_time":98.57749264},
{"learn":[1.015888646],"iteration":410,"passed_time":68.6514627,"remaining_time":98.38372635},
{"learn":[1.014982669],"iteration":411,"passed_time":68.81811143,"remaining_time":98.21613961},
{"learn":[1.014609188],"iteration":412,"passed_time":68.9724428,"remaining_time":98.03105066},
{"learn":[1.014278728],"iteration":413,"passed_time":69.13112009,"remaining_time":97.85226177},
{"learn":[1.013916826],"iteration":414,"passed_time":69.28577016,"remaining_time":97.66789288},
{"learn":[1.013354268],"iteration":415,"passed_time":69.4707549,"remaining_time":97.52625207},
{"learn":[1.013019984],"iteration":416,"passed_time":69.62774002,"remaining_time":97.34525763},
{"learn":[1.012462524],"iteration":417,"passed_time":69.77674114,"remaining_time":97.15326159},
{"learn":[1.011655547],"iteration":418,"passed_time":69.94690809,"remaining_time":96.99082005},
{"learn":[1.011258591],"iteration":419,"passed_time":70.10283413,"remaining_time":96.80867571},
{"learn":[1.010139743],"iteration":420,"passed_time":70.26103974,"remaining_time":96.629791},
{"learn":[1.009910301],"iteration":421,"passed_time":70.41127993,"remaining_time":96.44009431},
{"learn":[1.008996463],"iteration":422,"passed_time":70.55918431,"remaining_time":96.24739798},
{"learn":[1.00756978],"iteration":423,"passed_time":70.74185119,"remaining_time":96.10213746},
{"learn":[1.007150411],"iteration":424,"passed_time":70.89131294,"remaining_time":95.91177633},
{"learn":[1.005387426],"iteration":425,"passed_time":71.06967677,"remaining_time":95.76055039},
{"learn":[1.004321795],"iteration":426,"passed_time":71.23172748,"remaining_time":95.58730643},
{"learn":[1.003631982],"iteration":427,"passed_time":71.40595586,"remaining_time":95.43038961},
{"learn":[1.003019818],"iteration":428,"passed_time":71.55884801,"remaining_time":95.24499351},
{"learn":[1.002704229],"iteration":429,"passed_time":71.7103113,"remaining_time":95.05785451},
{"learn":[1.0022736],"iteration":430,"passed_time":71.85090297,"remaining_time":94.85652852},
{"learn":[1.001797402],"iteration":431,"passed_time":72.00587375,"remaining_time":94.67438956},
{"learn":[1.000939544],"iteration":432,"passed_time":72.16958757,"remaining_time":94.50382483},
{"learn":[1.00044072],"iteration":433,"passed_time":72.33033431,"remaining_time":94.32942217},
{"learn":[1.000033779],"iteration":434,"passed_time":72.49205393,"remaining_time":94.15634591},
{"learn":[0.9992559069],"iteration":435,"passed_time":72.65216334,"remaining_time":93.98123882},
{"learn":[0.99821492],"iteration":436,"passed_time":72.80242046,"remaining_time":93.79350736},
{"learn":[0.9974968515],"iteration":437,"passed_time":72.9723609,"remaining_time":93.6312028},
{"learn":[0.9972805812],"iteration":438,"passed_time":73.12584497,"remaining_time":93.44783378},
{"learn":[0.9965340449],"iteration":439,"passed_time":73.28144704,"remaining_time":93.26729624},
{"learn":[0.9963609012],"iteration":440,"passed_time":73.42629377,"remaining_time":93.07323859},
{"learn":[0.9955918456],"iteration":441,"passed_time":73.59763415,"remaining_time":92.91285035},
{"learn":[0.9949837181],"iteration":442,"passed_time":73.74510183,"remaining_time":92.72239666},
{"learn":[0.9940519287],"iteration":443,"passed_time":73.90371383,"remaining_time":92.54609209},
{"learn":[0.9934987185],"iteration":444,"passed_time":74.05129418,"remaining_time":92.35610847},
{"learn":[0.9932720383],"iteration":445,"passed_time":74.19203822,"remaining_time":92.15782326},
{"learn":[0.99282059],"iteration":446,"passed_time":74.36726521,"remaining_time":92.00245562},
{"learn":[0.9924866244],"iteration":447,"passed_time":74.51874616,"remaining_time":91.8177408},
{"learn":[0.9912620839],"iteration":448,"passed_time":74.67741,"remaining_time":91.64198867},
{"learn":[0.9900995778],"iteration":449,"passed_time":74.84109502,"remaining_time":91.47244946},
{"learn":[0.989335621],"iteration":450,"passed_time":75.00393563,"remaining_time":91.30190834},
{"learn":[0.9889760556],"iteration":451,"passed_time":75.14865567,"remaining_time":91.10943209},
{"learn":[0.9883605987],"iteration":452,"passed_time":75.31208782,"remaining_time":90.93976168},
{"learn":[0.9881649357],"iteration":453,"passed_time":75.45000085,"remaining_time":90.73942834},
{"learn":[0.9875732727],"iteration":454,"passed_time":75.61049918,"remaining_time":90.56642209},
{"learn":[0.9870501237],"iteration":455,"passed_time":75.77598637,"remaining_time":90.39942234},
{"learn":[0.9858452346],"iteration":456,"passed_time":75.94717054,"remaining_time":90.23919826},
{"learn":[0.9849718679],"iteration":457,"passed_time":76.11186846,"remaining_time":90.07125045},
{"learn":[0.9841347232],"iteration":458,"passed_time":76.26511072,"remaining_time":89.8898146},
{"learn":[0.9839392727],"iteration":459,"passed_time":76.41846395,"remaining_time":89.70863159},
{"learn":[0.9834748651],"iteration":460,"passed_time":76.56651395,"remaining_time":89.5213688},
{"learn":[0.982417095],"iteration":461,"passed_time":76.71567708,"remaining_time":89.33557201},
{"learn":[0.9817434278],"iteration":462,"passed_time":76.88309324,"remaining_time":89.17110383},
{"learn":[0.9814503581],"iteration":463,"passed_time":77.01848847,"remaining_time":88.96963324},
{"learn":[0.9807917746],"iteration":464,"passed_time":77.17948657,"remaining_time":88.79790391},
{"learn":[0.9806564463],"iteration":465,"passed_time":77.33349572,"remaining_time":88.61821183},
{"learn":[0.9790422794],"iteration":466,"passed_time":77.48272418,"remaining_time":88.43317342},
{"learn":[0.9779506241],"iteration":467,"passed_time":77.64647337,"remaining_time":88.26479451},
{"learn":[0.976920472],"iteration":468,"passed_time":77.80317762,"remaining_time":88.08845909},
{"learn":[0.975533835],"iteration":469,"passed_time":77.96932863,"remaining_time":87.92285994},
{"learn":[0.9743064266],"iteration":470,"passed_time":78.14158023,"remaining_time":87.76411028},
{"learn":[0.9732361222],"iteration":471,"passed_time":78.34614244,"remaining_time":87.64144748},
{"learn":[0.9728560557],"iteration":472,"passed_time":78.51909856,"remaining_time":87.48322398},
{"learn":[0.9725349432],"iteration":473,"passed_time":78.66688354,"remaining_time":87.29700578},
{"learn":[0.9717115013],"iteration":474,"passed_time":78.83895714,"remaining_time":87.13779474},
{"learn":[0.9707527312],"iteration":475,"passed_time":79.00138538,"remaining_time":86.96791164},
{"learn":[0.970066211],"iteration":476,"passed_time":79.15870373,"remaining_time":86.79245713},
{"learn":[0.9694070964],"iteration":477,"passed_time":79.3321619,"remaining_time":86.634704},
{"learn":[0.9686286932],"iteration":478,"passed_time":79.48943293,"remaining_time":86.45927882},
{"learn":[0.9681186096],"iteration":479,"passed_time":79.65242258,"remaining_time":86.29012446},
{"learn":[0.9673969296],"iteration":480,"passed_time":79.83168518,"remaining_time":86.13855428},
{"learn":[0.9665635027],"iteration":481,"passed_time":79.99800576,"remaining_time":85.97296055},
{"learn":[0.9661280941],"iteration":482,"passed_time":80.1519238,"remaining_time":85.79408821},
{"learn":[0.9658008206],"iteration":483,"passed_time":80.31156503,"remaining_time":85.62142057},
{"learn":[0.9651944988],"iteration":484,"passed_time":80.47050072,"remaining_time":85.44805747},
{"learn":[0.964336322],"iteration":485,"passed_time":80.62343123,"remaining_time":85.26840258},
{"learn":[0.9635253083],"iteration":486,"passed_time":80.77647869,"remaining_time":85.08898063},
{"learn":[0.9630910681],"iteration":487,"passed_time":80.92943966,"remaining_time":84.90957603},
{"learn":[0.9626639448],"iteration":488,"passed_time":81.08864572,"remaining_time":84.73680565},
{"learn":[0.9621814793],"iteration":489,"passed_time":81.26848806,"remaining_time":84.5855692},
{"learn":[0.9618447519],"iteration":490,"passed_time":81.41821132,"remaining_time":84.402993},
{"learn":[0.9614947466],"iteration":491,"passed_time":81.58422984,"remaining_time":84.23737553},
{"learn":[0.9601925571],"iteration":492,"passed_time":81.77407136,"remaining_time":84.09625594},
{"learn":[0.9595487386],"iteration":493,"passed_time":81.93555298,"remaining_time":83.9258903},
{"learn":[0.9586535961],"iteration":494,"passed_time":82.10202168,"remaining_time":83.76064838},
{"learn":[0.9584584642],"iteration":495,"passed_time":82.24787608,"remaining_time":83.57445473},
{"learn":[0.9581843023],"iteration":496,"passed_time":82.40010798,"remaining_time":83.3948779},
{"learn":[0.9580337841],"iteration":497,"passed_time":82.54178491,"remaining_time":83.20477113},
{"learn":[0.9567415795],"iteration":498,"passed_time":82.7567995,"remaining_time":83.08849008},
{"learn":[0.9562427556],"iteration":499,"passed_time":82.92785585,"remaining_time":82.92785585},
{"learn":[0.9556020176],"iteration":500,"passed_time":83.0949476,"remaining_time":82.76323124},
{"learn":[0.9546079814],"iteration":501,"passed_time":83.25982064,"remaining_time":82.59639577},
{"learn":[0.9541477165],"iteration":502,"passed_time":83.4376221,"remaining_time":82.44234232},
{"learn":[0.9529909464],"iteration":503,"passed_time":83.61930666,"remaining_time":82.29201608},
{"learn":[0.9516319274],"iteration":504,"passed_time":83.79824427,"remaining_time":82.1388731},
{"learn":[0.9513920756],"iteration":505,"passed_time":83.94958692,"remaining_time":81.95868762},
{"learn":[0.9508558611],"iteration":506,"passed_time":84.1163538,"remaining_time":81.79361425},
{"learn":[0.9502599493],"iteration":507,"passed_time":84.27630789,"remaining_time":81.62193599},
{"learn":[0.9497373314],"iteration":508,"passed_time":84.42780005,"remaining_time":81.44214111},
{"learn":[0.9490116149],"iteration":509,"passed_time":84.59018288,"remaining_time":81.27292081},
{"learn":[0.9478943598],"iteration":510,"passed_time":84.75517516,"remaining_time":81.10622437},
{"learn":[0.9472648814],"iteration":511,"passed_time":84.92176742,"remaining_time":80.94105957},
{"learn":[0.9467290919],"iteration":512,"passed_time":85.08540988,"remaining_time":80.77308891},
{"learn":[0.9463658087],"iteration":513,"passed_time":85.22910174,"remaining_time":80.58627129},
{"learn":[0.9459239204],"iteration":514,"passed_time":85.38078242,"remaining_time":80.40714461},
{"learn":[0.9454274334],"iteration":515,"passed_time":85.53412826,"remaining_time":80.22968619},
{"learn":[0.944044833],"iteration":516,"passed_time":85.69858516,"remaining_time":80.06270141},
{"learn":[0.9432834255],"iteration":517,"passed_time":85.85898576,"remaining_time":79.89195201},
{"learn":[0.9430976412],"iteration":518,"passed_time":86.00682916,"remaining_time":79.70960468},
{"learn":[0.9428506724],"iteration":519,"passed_time":86.16417937,"remaining_time":79.53616557},
{"learn":[0.9420938324],"iteration":520,"passed_time":86.31652758,"remaining_time":79.35818947},
{"learn":[0.9414112425],"iteration":521,"passed_time":86.4947116,"remaining_time":79.20396962},
{"learn":[0.9408834197],"iteration":522,"passed_time":86.64782976,"remaining_time":79.02679693},
{"learn":[0.9403654756],"iteration":523,"passed_time":86.79943552,"remaining_time":78.84834219},
{"learn":[0.9392816808],"iteration":524,"passed_time":86.96162178,"remaining_time":78.67956256},
{"learn":[0.9385979224],"iteration":525,"passed_time":87.12759978,"remaining_time":78.5142249},
{"learn":[0.9377912639],"iteration":526,"passed_time":87.28833408,"remaining_time":78.34417841},
{"learn":[0.9366027331],"iteration":527,"passed_time":87.45902436,"remaining_time":78.18306723},
{"learn":[0.9361279156],"iteration":528,"passed_time":87.61492029,"remaining_time":78.00874756},
{"learn":[0.9355705628],"iteration":529,"passed_time":87.77271981,"remaining_time":77.83618549},
{"learn":[0.9348420844],"iteration":530,"passed_time":87.93728417,"remaining_time":77.669654},
{"learn":[0.9340441361],"iteration":531,"passed_time":88.11268916,"remaining_time":77.5126664},
{"learn":[0.933459059],"iteration":532,"passed_time":88.28390484,"remaining_time":77.35193914},
{"learn":[0.9329010689],"iteration":533,"passed_time":88.43768675,"remaining_time":77.17595885},
{"learn":[0.9323641109],"iteration":534,"passed_time":88.6030485,"remaining_time":77.01012627},
{"learn":[0.9316293653],"iteration":535,"passed_time":88.7578168,"remaining_time":76.83512499},
{"learn":[0.9311796165],"iteration":536,"passed_time":88.91694672,"remaining_time":76.66395965},
{"learn":[0.9310559728],"iteration":537,"passed_time":89.06578368,"remaining_time":76.48400012},
{"learn":[0.9299218283],"iteration":538,"passed_time":89.23928974,"remaining_time":76.32525524},
{"learn":[0.929456146],"iteration":539,"passed_time":89.39739617,"remaining_time":76.15333748},
{"learn":[0.9288072288],"iteration":540,"passed_time":89.5581646,"remaining_time":75.9837293},
{"learn":[0.9282699521],"iteration":541,"passed_time":89.70960633,"remaining_time":75.80627251},
{"learn":[0.9276336755],"iteration":542,"passed_time":89.89060681,"remaining_time":75.65378879},
{"learn":[0.9269051971],"iteration":543,"passed_time":90.05152014,"remaining_time":75.48436247},
{"learn":[0.9257880483],"iteration":544,"passed_time":90.22583004,"remaining_time":75.32615169},
{"learn":[0.9250402373],"iteration":545,"passed_time":90.38496249,"remaining_time":75.15526185},
{"learn":[0.9244485744],"iteration":546,"passed_time":90.54307144,"remaining_time":74.98356739},
{"learn":[0.9238984447],"iteration":547,"passed_time":90.70304787,"remaining_time":74.81346284},
{"learn":[0.9232455973],"iteration":548,"passed_time":90.8536323,"remaining_time":74.63567972},
{"learn":[0.9228019032],"iteration":549,"passed_time":91.01717534,"remaining_time":74.46859801},
{"learn":[0.9219748498],"iteration":550,"passed_time":91.19103117,"remaining_time":74.30993284},
{"learn":[0.9214120795],"iteration":551,"passed_time":91.35316235,"remaining_time":74.14169698},
{"learn":[0.9206849821],"iteration":552,"passed_time":91.50901465,"remaining_time":73.96840786},
{"learn":[0.920401685],"iteration":553,"passed_time":91.66600383,"remaining_time":73.79609695},
{"learn":[0.9196018247],"iteration":554,"passed_time":91.83958083,"remaining_time":73.63714139},
{"learn":[0.9189444096],"iteration":555,"passed_time":92.02029154,"remaining_time":73.48382993},
{"learn":[0.9185855878],"iteration":556,"passed_time":92.17723594,"remaining_time":73.31151799},
{"learn":[0.9177992179],"iteration":557,"passed_time":92.34251216,"remaining_time":73.14586089},
{"learn":[0.9172379348],"iteration":558,"passed_time":92.50142785,"remaining_time":72.97518727},
{"learn":[0.9169142728],"iteration":559,"passed_time":92.64578082,"remaining_time":72.7931135},
{"learn":[0.9166259832],"iteration":560,"passed_time":92.80249348,"remaining_time":72.62084606},
{"learn":[0.9163771024],"iteration":561,"passed_time":92.96472779,"remaining_time":72.45293731},
{"learn":[0.9160177495],"iteration":562,"passed_time":93.11924627,"remaining_time":72.27905972},
{"learn":[0.9154409578],"iteration":563,"passed_time":93.28082867,"remaining_time":72.11071153},
{"learn":[0.9139039088],"iteration":564,"passed_time":93.46058781,"remaining_time":71.95638176},
{"learn":[0.9136422812],"iteration":565,"passed_time":93.6173831,"remaining_time":71.78435382},
{"learn":[0.9129586291],"iteration":566,"passed_time":93.78013104,"remaining_time":71.61692546},
{"learn":[0.9120485091],"iteration":567,"passed_time":93.95680186,"remaining_time":71.46010283},
{"learn":[0.9115551026],"iteration":568,"passed_time":94.11626042,"remaining_time":71.29017266},
{"learn":[0.9109189322],"iteration":569,"passed_time":94.28621695,"remaining_time":71.12819875},
{"learn":[0.9099675977],"iteration":570,"passed_time":94.45629751,"remaining_time":70.96629008},
{"learn":[0.9094557083],"iteration":571,"passed_time":94.61590215,"remaining_time":70.7965142},
{"learn":[0.9091216366],"iteration":572,"passed_time":94.76887559,"remaining_time":70.62183224},
{"learn":[0.9090849896],"iteration":573,"passed_time":94.9097962,"remaining_time":70.4382808},
{"learn":[0.9088577783],"iteration":574,"passed_time":95.06444868,"remaining_time":70.26502728},
{"learn":[0.908283111],"iteration":575,"passed_time":95.22783569,"remaining_time":70.09826794},
{"learn":[0.9076338752],"iteration":576,"passed_time":95.39872643,"remaining_time":69.93702128},
{"learn":[0.9066640578],"iteration":577,"passed_time":95.57737333,"remaining_time":69.78140406},
{"learn":[0.9059290999],"iteration":578,"passed_time":95.74152123,"remaining_time":69.61516483},
{"learn":[0.9052511838],"iteration":579,"passed_time":95.91581006,"remaining_time":69.45627625},
{"learn":[0.9047941056],"iteration":580,"passed_time":96.08347494,"remaining_time":69.29255766},
{"learn":[0.9044802162],"iteration":581,"passed_time":96.23667913,"remaining_time":69.11843965},
{"learn":[0.9040008311],"iteration":582,"passed_time":96.39798758,"remaining_time":68.95019009},
{"learn":[0.9029872498],"iteration":583,"passed_time":96.56683178,"remaining_time":68.78733223},
{"learn":[0.9024872575],"iteration":584,"passed_time":96.72341136,"remaining_time":68.61575336},
{"learn":[0.9020651267],"iteration":585,"passed_time":96.8840952,"remaining_time":68.44712528},
{"learn":[0.901542615],"iteration":586,"passed_time":97.06403238,"remaining_time":68.29207048},
{"learn":[0.9004826142],"iteration":587,"passed_time":97.2340982,"remaining_time":68.13001439},
{"learn":[0.8992708206],"iteration":588,"passed_time":97.41676618,"remaining_time":67.97672479},
{"learn":[0.8990412724],"iteration":589,"passed_time":97.56503608,"remaining_time":67.79943185},
{"learn":[0.8981906374],"iteration":590,"passed_time":97.73686081,"remaining_time":67.63853819},
{"learn":[0.8975132524],"iteration":591,"passed_time":97.90649194,"remaining_time":67.4760958},
{"learn":[0.8971530497],"iteration":592,"passed_time":98.05978501,"remaining_time":67.30241568},
{"learn":[0.8968832429],"iteration":593,"passed_time":98.21495705,"remaining_time":67.13008849},
{"learn":[0.8951007123],"iteration":594,"passed_time":98.38415101,"remaining_time":66.96736329},
{"learn":[0.894655956],"iteration":595,"passed_time":98.54351923,"remaining_time":66.79795599},
{"learn":[0.8938848822],"iteration":596,"passed_time":98.7009345,"remaining_time":66.62726399},
{"learn":[0.8928445327],"iteration":597,"passed_time":98.87760581,"remaining_time":66.4695611},
{"learn":[0.8919787078],"iteration":598,"passed_time":99.04444378,"remaining_time":66.30521195},
{"learn":[0.8913035535],"iteration":599,"passed_time":99.2303859,"remaining_time":66.1535906},
{"learn":[0.8907169892],"iteration":600,"passed_time":99.4040706,"remaining_time":65.99371742},
{"learn":[0.8905172897],"iteration":601,"passed_time":99.5545563,"remaining_time":65.81846081},
{"learn":[0.8901822619],"iteration":602,"passed_time":99.72177686,"remaining_time":65.65430417},
{"learn":[0.8899383205],"iteration":603,"passed_time":99.88277101,"remaining_time":65.48605517},
{"learn":[0.8894241473],"iteration":604,"passed_time":100.0534465,"remaining_time":65.32415101},
{"learn":[0.8887150547],"iteration":605,"passed_time":100.2074334,"remaining_time":65.15136761},
{"learn":[0.8886089909],"iteration":606,"passed_time":100.3628942,"remaining_time":64.97960035},
{"learn":[0.8881338016],"iteration":607,"passed_time":100.5294236,"remaining_time":64.81502313},
{"learn":[0.8873696323],"iteration":608,"passed_time":100.7199215,"remaining_time":64.6658281},
{"learn":[0.8867512543],"iteration":609,"passed_time":100.8960787,"remaining_time":64.50732904},
{"learn":[0.8865124646],"iteration":610,"passed_time":101.0415626,"remaining_time":64.32924364},
{"learn":[0.8862667705],"iteration":611,"passed_time":101.1888472,"remaining_time":64.15240642},
{"learn":[0.8861700012],"iteration":612,"passed_time":101.3333035,"remaining_time":63.97388},
{"learn":[0.8853957407],"iteration":613,"passed_time":101.488288,"remaining_time":63.80208335},
{"learn":[0.884167748],"iteration":614,"passed_time":101.6572982,"remaining_time":63.63912167},
{"learn":[0.8835630728],"iteration":615,"passed_time":101.8204546,"remaining_time":63.47249118},
{"learn":[0.883132391],"iteration":616,"passed_time":101.9754906,"remaining_time":63.30083129},
{"learn":[0.8825761535],"iteration":617,"passed_time":102.1469789,"remaining_time":63.13939472},
{"learn":[0.8822125517],"iteration":618,"passed_time":102.2967858,"remaining_time":62.96458059},
{"learn":[0.8809195504],"iteration":619,"passed_time":102.4592959,"remaining_time":62.79763295},
{"learn":[0.8802620291],"iteration":620,"passed_time":102.6120635,"remaining_time":62.6247537},
{"learn":[0.8800084214],"iteration":621,"passed_time":102.7621115,"remaining_time":62.45028641},
{"learn":[0.87959123],"iteration":622,"passed_time":102.9280212,"remaining_time":62.28549596},
{"learn":[0.8789333369],"iteration":623,"passed_time":103.0863121,"remaining_time":62.11611115},
{"learn":[0.8785567758],"iteration":624,"passed_time":103.2499686,"remaining_time":61.94998116},
{"learn":[0.8776506924],"iteration":625,"passed_time":103.4244773,"remaining_time":61.79034268},
{"learn":[0.8765802818],"iteration":626,"passed_time":103.610133,"remaining_time":61.63728804},
{"learn":[0.8761560265],"iteration":627,"passed_time":103.7737254,"remaining_time":61.47106026},
{"learn":[0.8758291779],"iteration":628,"passed_time":103.9310917,"remaining_time":61.30116857},
{"learn":[0.8752088347],"iteration":629,"passed_time":104.1144694,"remaining_time":61.14659316},
{"learn":[0.8751515273],"iteration":630,"passed_time":104.2668963,"remaining_time":60.97382686},
{"learn":[0.8747495789],"iteration":631,"passed_time":104.434082,"remaining_time":60.80971866},
{"learn":[0.8743677067],"iteration":632,"passed_time":104.6038914,"remaining_time":60.64712185},
{"learn":[0.8737185771],"iteration":633,"passed_time":104.7617979,"remaining_time":60.47763099},
{"learn":[0.8724615855],"iteration":634,"passed_time":104.9370553,"remaining_time":60.31814987},
{"learn":[0.8715104634],"iteration":635,"passed_time":105.1169945,"remaining_time":60.16129874},
{"learn":[0.8708218187],"iteration":636,"passed_time":105.2848686,"remaining_time":59.99749972},
{"learn":[0.8693665616],"iteration":637,"passed_time":105.4654393,"remaining_time":59.84089192},
{"learn":[0.868834065],"iteration":638,"passed_time":105.6340835,"remaining_time":59.6774713},
{"learn":[0.8680432868],"iteration":639,"passed_time":105.7889077,"remaining_time":59.50626056},
{"learn":[0.8671676894],"iteration":640,"passed_time":105.9601113,"remaining_time":59.34427451},
{"learn":[0.8669592796],"iteration":641,"passed_time":106.1130988,"remaining_time":59.17210183},
{"learn":[0.8663329348],"iteration":642,"passed_time":106.2821834,"remaining_time":59.00892607},
{"learn":[0.8658277906],"iteration":643,"passed_time":106.447365,"remaining_time":58.84357444},
{"learn":[0.8653488304],"iteration":644,"passed_time":106.6105972,"remaining_time":58.67715042},
{"learn":[0.8649405618],"iteration":645,"passed_time":106.7668776,"remaining_time":58.50692671},
{"learn":[0.8645200774],"iteration":646,"passed_time":106.9325024,"remaining_time":58.34184445},
{"learn":[0.8638937327],"iteration":647,"passed_time":107.1197932,"remaining_time":58.18852965},
{"learn":[0.8633485424],"iteration":648,"passed_time":107.2791814,"remaining_time":58.02001955},
{"learn":[0.8631463997],"iteration":649,"passed_time":107.4220095,"remaining_time":57.84262049},
{"learn":[0.8618406517],"iteration":650,"passed_time":107.6041829,"remaining_time":57.68642062},
{"learn":[0.8616821136],"iteration":651,"passed_time":107.7590374,"remaining_time":57.51555983},
{"learn":[0.8614798117],"iteration":652,"passed_time":107.9056876,"remaining_time":57.34038837},
{"learn":[0.8610009577],"iteration":653,"passed_time":108.0751256,"remaining_time":57.17736004},
{"learn":[0.8603703109],"iteration":654,"passed_time":108.2377892,"remaining_time":57.01074394},
{"learn":[0.8597581469],"iteration":655,"passed_time":108.3967734,"remaining_time":56.84221045},
{"learn":[0.8593910928],"iteration":656,"passed_time":108.5517985,"remaining_time":56.6716391},
{"learn":[0.8590310495],"iteration":657,"passed_time":108.7084286,"remaining_time":56.5019492},
{"learn":[0.8588717147],"iteration":658,"passed_time":108.8723121,"remaining_time":56.33605223},
{"learn":[0.85829965],"iteration":659,"passed_time":109.0343741,"remaining_time":56.16922301},
{"learn":[0.8566120297],"iteration":660,"passed_time":109.225361,"remaining_time":56.01724262},
{"learn":[0.8562378056],"iteration":661,"passed_time":109.3819687,"remaining_time":55.84759127},
{"learn":[0.8552319255],"iteration":662,"passed_time":109.54206,"remaining_time":55.67974995},
{"learn":[0.8543211682],"iteration":663,"passed_time":109.7121083,"remaining_time":55.51697047},
{"learn":[0.8539584162],"iteration":664,"passed_time":109.8773236,"remaining_time":55.35173442},
{"learn":[0.8535233793],"iteration":665,"passed_time":110.0656114,"remaining_time":55.1980694},
{"learn":[0.8527258028],"iteration":666,"passed_time":110.243336,"remaining_time":55.0390268},
{"learn":[0.8517066979],"iteration":667,"passed_time":110.4242634,"remaining_time":54.88152016},
{"learn":[0.8511804685],"iteration":668,"passed_time":110.5927973,"remaining_time":54.71781153},
{"learn":[0.8505208227],"iteration":669,"passed_time":110.7602783,"remaining_time":54.55356991},
{"learn":[0.8499468459],"iteration":670,"passed_time":110.9262973,"remaining_time":54.38860178},
{"learn":[0.849734559],"iteration":671,"passed_time":111.0900117,"remaining_time":54.22250569},
{"learn":[0.8492459325],"iteration":672,"passed_time":111.2516458,"remaining_time":54.05540593},
{"learn":[0.8485922884],"iteration":673,"passed_time":111.416868,"remaining_time":53.89005782},
{"learn":[0.8478538251],"iteration":674,"passed_time":111.588802,"remaining_time":53.72794172},
{"learn":[0.8477488766],"iteration":675,"passed_time":111.7325668,"remaining_time":53.55229532},
{"learn":[0.8470518403],"iteration":676,"passed_time":111.9186345,"remaining_time":53.39692605},
{"learn":[0.8463980899],"iteration":677,"passed_time":112.0853074,"remaining_time":53.23225515},
{"learn":[0.8457760472],"iteration":678,"passed_time":112.2443537,"remaining_time":53.06397282},
{"learn":[0.8453337871],"iteration":679,"passed_time":112.3960989,"remaining_time":52.89228185},
{"learn":[0.8450171359],"iteration":680,"passed_time":112.5625755,"remaining_time":52.72755007},
{"learn":[0.8448609879],"iteration":681,"passed_time":112.722915,"remaining_time":52.55995155},
{"learn":[0.8444084773],"iteration":682,"passed_time":112.9034578,"remaining_time":52.40175127},
{"learn":[0.8436240725],"iteration":683,"passed_time":113.0855988,"remaining_time":52.24422399},
{"learn":[0.8432568059],"iteration":684,"passed_time":113.2400372,"remaining_time":52.07388572},
{"learn":[0.8428362685],"iteration":685,"passed_time":113.3904753,"remaining_time":51.90176273},
{"learn":[0.8425815985],"iteration":686,"passed_time":113.5440816,"remaining_time":51.73114633},
{"learn":[0.8420966367],"iteration":687,"passed_time":113.7128897,"remaining_time":51.56747323},
{"learn":[0.8419460123],"iteration":688,"passed_time":113.8665553,"remaining_time":51.39695021},
{"learn":[0.8415330167],"iteration":689,"passed_time":114.0168993,"remaining_time":51.22498373},
{"learn":[0.8412312899],"iteration":690,"passed_time":114.1708577,"remaining_time":51.05469614},
{"learn":[0.8408375738],"iteration":691,"passed_time":114.3252249,"remaining_time":50.88463769},
{"learn":[0.8402574892],"iteration":692,"passed_time":114.4997967,"remaining_time":50.72357518},
{"learn":[0.839648087],"iteration":693,"passed_time":114.6656663,"remaining_time":50.55863673},
{"learn":[0.8392660023],"iteration":694,"passed_time":114.8282469,"remaining_time":50.39225225},
{"learn":[0.8389735169],"iteration":695,"passed_time":114.9882221,"remaining_time":50.2247407},
{"learn":[0.8381641496],"iteration":696,"passed_time":115.1700443,"remaining_time":50.06674808},
{"learn":[0.8372111686],"iteration":697,"passed_time":115.3428939,"remaining_time":49.90480512},
{"learn":[0.8368219139],"iteration":698,"passed_time":115.4995732,"remaining_time":49.7358677},
{"learn":[0.8357871942],"iteration":699,"passed_time":115.6864447,"remaining_time":49.57990485},
{"learn":[0.8350565383],"iteration":700,"passed_time":115.8566045,"remaining_time":49.41672575},
{"learn":[0.8342702746],"iteration":701,"passed_time":116.0176613,"remaining_time":49.24966247},
{"learn":[0.8336512061],"iteration":702,"passed_time":116.1725704,"remaining_time":49.08001909},
{"learn":[0.8333744417],"iteration":703,"passed_time":116.3350464,"remaining_time":48.91359907},
{"learn":[0.8329980931],"iteration":704,"passed_time":116.4901386,"remaining_time":48.74410057},
{"learn":[0.8326020401],"iteration":705,"passed_time":116.6470189,"remaining_time":48.57538746},
{"learn":[0.8316118279],"iteration":706,"passed_time":116.828922,"remaining_time":48.41707801},
{"learn":[0.8314726225],"iteration":707,"passed_time":116.9927358,"remaining_time":48.25124132},
{"learn":[0.8314141997],"iteration":708,"passed_time":117.1365971,"remaining_time":48.07722109},
{"learn":[0.8311364793],"iteration":709,"passed_time":117.2886589,"remaining_time":47.90663532},
{"learn":[0.8307550851],"iteration":710,"passed_time":117.4484248,"remaining_time":47.73923313},
{"learn":[0.8301193927],"iteration":711,"passed_time":117.6412506,"remaining_time":47.58522495},
{"learn":[0.8295456815],"iteration":712,"passed_time":117.7999765,"remaining_time":47.41738186},
{"learn":[0.8289481232],"iteration":713,"passed_time":117.9614167,"remaining_time":47.25065149},
{"learn":[0.8286753952],"iteration":714,"passed_time":118.1153739,"remaining_time":47.08095325},
{"learn":[0.8276423751],"iteration":715,"passed_time":118.2909166,"remaining_time":46.91986076},
{"learn":[0.8269746564],"iteration":716,"passed_time":118.4563384,"remaining_time":46.75473329},
{"learn":[0.8265395664],"iteration":717,"passed_time":118.630055,"remaining_time":46.59286283},
{"learn":[0.8261266239],"iteration":718,"passed_time":118.7900435,"remaining_time":46.4255942},
{"learn":[0.8258072109],"iteration":719,"passed_time":118.9560272,"remaining_time":46.26067726},
{"learn":[0.8253118924],"iteration":720,"passed_time":119.1170063,"remaining_time":46.09382074},
{"learn":[0.8243352768],"iteration":721,"passed_time":119.3003609,"remaining_time":45.93559602},
{"learn":[0.8236662303],"iteration":722,"passed_time":119.4678512,"remaining_time":45.77122375},
{"learn":[0.8234762502],"iteration":723,"passed_time":119.6162752,"remaining_time":45.59957453},
{"learn":[0.822943488],"iteration":724,"passed_time":119.8037314,"remaining_time":45.44279466},
{"learn":[0.8224290493],"iteration":725,"passed_time":119.9646792,"remaining_time":45.27592575},
{"learn":[0.8214329418],"iteration":726,"passed_time":120.1251429,"remaining_time":45.10889133},
{"learn":[0.8207794038],"iteration":727,"passed_time":120.3013104,"remaining_time":44.94774233},
{"learn":[0.8203646025],"iteration":728,"passed_time":120.4573725,"remaining_time":44.77907812},
{"learn":[0.8197796847],"iteration":729,"passed_time":120.6344136,"remaining_time":44.61820777},
{"learn":[0.8194578286],"iteration":730,"passed_time":120.8028954,"remaining_time":44.45414346},
{"learn":[0.8189603856],"iteration":731,"passed_time":120.9666682,"remaining_time":44.288343},
{"learn":[0.8182153895],"iteration":732,"passed_time":121.143716,"remaining_time":44.12738359},
{"learn":[0.8179678896],"iteration":733,"passed_time":121.2914933,"remaining_time":43.95577279},
{"learn":[0.8172637364],"iteration":734,"passed_time":121.4581559,"remaining_time":43.79103579},
{"learn":[0.816998922],"iteration":735,"passed_time":121.619093,"remaining_time":43.62423988},
{"learn":[0.8167521657],"iteration":736,"passed_time":121.7707256,"remaining_time":43.45413954},
{"learn":[0.8165360016],"iteration":737,"passed_time":121.9307173,"remaining_time":43.28705682},
{"learn":[0.8163656728],"iteration":738,"passed_time":122.0889714,"remaining_time":43.11937963},
{"learn":[0.8156362384],"iteration":739,"passed_time":122.2548933,"remaining_time":42.95442196},
{"learn":[0.8151902605],"iteration":740,"passed_time":122.4336258,"remaining_time":42.79393938},
{"learn":[0.8148907644],"iteration":741,"passed_time":122.5997921,"remaining_time":42.62903823},
{"learn":[0.8142814153],"iteration":742,"passed_time":122.7693469,"remaining_time":42.46530572},
{"learn":[0.8141547973],"iteration":743,"passed_time":122.9261573,"remaining_time":42.29717242},
{"learn":[0.8139729964],"iteration":744,"passed_time":123.076273,"remaining_time":42.126778},
{"learn":[0.8137501402],"iteration":745,"passed_time":123.2286068,"remaining_time":41.95719319},
{"learn":[0.8131320808],"iteration":746,"passed_time":123.4061325,"remaining_time":41.79618677},
{"learn":[0.8125087103],"iteration":747,"passed_time":123.5896805,"remaining_time":41.6371651},
{"learn":[0.8122052839],"iteration":748,"passed_time":123.7419806,"remaining_time":41.46760632},
{"learn":[0.8119663349],"iteration":749,"passed_time":123.8999237,"remaining_time":41.29997457},
{"learn":[0.8117975463],"iteration":750,"passed_time":124.0584513,"remaining_time":41.13256243},
{"learn":[0.8113220915],"iteration":751,"passed_time":124.2255077,"remaining_time":40.96798659},
{"learn":[0.8107936314],"iteration":752,"passed_time":124.4155574,"remaining_time":40.81094644},
{"learn":[0.8105232935],"iteration":753,"passed_time":124.5647882,"remaining_time":40.64050118},
{"learn":[0.8103639056],"iteration":754,"passed_time":124.7168336,"remaining_time":40.47102548},
{"learn":[0.8099980731],"iteration":755,"passed_time":124.8825027,"remaining_time":40.30599293},
{"learn":[0.8096941156],"iteration":756,"passed_time":125.0463923,"remaining_time":40.14038749},
{"learn":[0.8089658497],"iteration":757,"passed_time":125.2187851,"remaining_time":39.97750132},
{"learn":[0.8085674067],"iteration":758,"passed_time":125.4016709,"remaining_time":39.81792184},
{"learn":[0.8082288204],"iteration":759,"passed_time":125.5624872,"remaining_time":39.65131175},
{"learn":[0.8076925528],"iteration":760,"passed_time":125.7243041,"remaining_time":39.48503111},
{"learn":[0.806919089],"iteration":761,"passed_time":125.9274658,"remaining_time":39.33167567},
{"learn":[0.8064436873],"iteration":762,"passed_time":126.0926455,"remaining_time":39.16639186},
{"learn":[0.8059163956],"iteration":763,"passed_time":126.2917621,"remaining_time":39.01159144},
{"learn":[0.805137355],"iteration":764,"passed_time":126.4738315,"remaining_time":38.85143844},
{"learn":[0.8048578819],"iteration":765,"passed_time":126.6357078,"remaining_time":38.68505957},
{"learn":[0.8039928006],"iteration":766,"passed_time":126.8102779,"remaining_time":38.52254855},
{"learn":[0.8033075551],"iteration":767,"passed_time":126.9896476,"remaining_time":38.36145603},
{"learn":[0.8031363234],"iteration":768,"passed_time":127.1532198,"remaining_time":38.19557059},
{"learn":[0.8024217072],"iteration":769,"passed_time":127.3434201,"remaining_time":38.03764498},
{"learn":[0.8020355329],"iteration":770,"passed_time":127.4938826,"remaining_time":37.86783284},
{"learn":[0.8017238742],"iteration":771,"passed_time":127.6561271,"remaining_time":37.7015505},
{"learn":[0.8009187028],"iteration":772,"passed_time":127.8589392,"remaining_time":37.54719171},
{"learn":[0.8001090168],"iteration":773,"passed_time":128.0265438,"remaining_time":37.38242751},
{"learn":[0.7995780073],"iteration":774,"passed_time":128.1945324,"remaining_time":37.21776748},
{"learn":[0.799148972],"iteration":775,"passed_time":128.3563085,"remaining_time":37.05130554},
{"learn":[0.7988752881],"iteration":776,"passed_time":128.5102777,"remaining_time":36.88261508},
{"learn":[0.7985540693],"iteration":777,"passed_time":128.6759919,"remaining_time":36.71731387},
{"learn":[0.7982759771],"iteration":778,"passed_time":128.8607543,"remaining_time":36.55741552},
{"learn":[0.7976800652],"iteration":779,"passed_time":129.0297291,"remaining_time":36.39300051},
{"learn":[0.7968319796],"iteration":780,"passed_time":129.2344678,"remaining_time":36.23860236},
{"learn":[0.7966780623],"iteration":781,"passed_time":129.4103136,"remaining_time":36.07602093},
{"learn":[0.7955267627],"iteration":782,"passed_time":129.6160512,"remaining_time":35.92168981},
{"learn":[0.7950562473],"iteration":783,"passed_time":129.7887595,"remaining_time":35.75812762},
{"learn":[0.7946602474],"iteration":784,"passed_time":129.9650042,"remaining_time":35.5955107},
{"learn":[0.7944251756],"iteration":785,"passed_time":130.125671,"remaining_time":35.42861781},
{"learn":[0.7933591732],"iteration":786,"passed_time":130.2945256,"remaining_time":35.26395673},
{"learn":[0.7927490805],"iteration":787,"passed_time":130.4718671,"remaining_time":35.1015683},
{"learn":[0.7922015533],"iteration":788,"passed_time":130.6586341,"remaining_time":34.94166261},
{"learn":[0.7918059252],"iteration":789,"passed_time":130.8431927,"remaining_time":34.78110185},
{"learn":[0.791560178],"iteration":790,"passed_time":131.0151825,"remaining_time":34.61715948},
{"learn":[0.7913519806],"iteration":791,"passed_time":131.1708662,"remaining_time":34.44891436},
{"learn":[0.7908232549],"iteration":792,"passed_time":131.3496959,"remaining_time":34.28674282},
{"learn":[0.7905069755],"iteration":793,"passed_time":131.5049448,"remaining_time":34.11841138},
{"learn":[0.7901814015],"iteration":794,"passed_time":131.6698457,"remaining_time":33.95260172},
{"learn":[0.7898629445],"iteration":795,"passed_time":131.8299054,"remaining_time":33.78555366},
{"learn":[0.7895130455],"iteration":796,"passed_time":131.9842262,"remaining_time":33.61706137},
{"learn":[0.7891163551],"iteration":797,"passed_time":132.1472346,"remaining_time":33.45080374},
{"learn":[0.7885611799],"iteration":798,"passed_time":132.3161509,"remaining_time":33.28604046},
{"learn":[0.7880371811],"iteration":799,"passed_time":132.4856205,"remaining_time":33.12140513},
{"learn":[0.7872779511],"iteration":800,"passed_time":132.6453151,"remaining_time":32.95432923},
{"learn":[0.7864162159],"iteration":801,"passed_time":132.8197437,"remaining_time":32.79090928},
{"learn":[0.7858932793],"iteration":802,"passed_time":132.9973677,"remaining_time":32.62824587},
{"learn":[0.7848875586],"iteration":803,"passed_time":133.1744934,"remaining_time":32.46542376},
{"learn":[0.7847657737],"iteration":804,"passed_time":133.324271,"remaining_time":32.29594142},
{"learn":[0.7839134923],"iteration":805,"passed_time":133.4848608,"remaining_time":32.12911043},
{"learn":[0.7833859881],"iteration":806,"passed_time":133.6667331,"remaining_time":31.96738474},
{"learn":[0.7827326627],"iteration":807,"passed_time":133.8481117,"remaining_time":31.80549188},
{"learn":[0.781718391],"iteration":808,"passed_time":134.0123496,"remaining_time":31.63950404},
{"learn":[0.7811906744],"iteration":809,"passed_time":134.1732743,"remaining_time":31.47274336},
{"learn":[0.7809518316],"iteration":810,"passed_time":134.3318209,"remaining_time":31.30544285},
{"learn":[0.7806077217],"iteration":811,"passed_time":134.4770773,"remaining_time":31.13508686},
{"learn":[0.7803585754],"iteration":812,"passed_time":134.6431458,"remaining_time":30.96957965},
{"learn":[0.7799321425],"iteration":813,"passed_time":134.7910123,"remaining_time":30.79991189},
{"learn":[0.7797125793],"iteration":814,"passed_time":134.9555186,"remaining_time":30.63407477},
{"learn":[0.7792686728],"iteration":815,"passed_time":135.1218046,"remaining_time":30.46864221},
{"learn":[0.7790922361],"iteration":816,"passed_time":135.2825654,"remaining_time":30.30196996},
{"learn":[0.7786492325],"iteration":817,"passed_time":135.4614864,"remaining_time":30.13935273},
{"learn":[0.7778323765],"iteration":818,"passed_time":135.6438187,"remaining_time":29.97744955},
{"learn":[0.77670349],"iteration":819,"passed_time":135.8362047,"remaining_time":29.81770348},
{"learn":[0.7764041],"iteration":820,"passed_time":135.9920208,"remaining_time":29.64990465},
{"learn":[0.7759088877],"iteration":821,"passed_time":136.1664603,"remaining_time":29.4861678},
{"learn":[0.775623413],"iteration":822,"passed_time":136.3448929,"remaining_time":29.32326373},
{"learn":[0.7749539948],"iteration":823,"passed_time":136.5105339,"remaining_time":29.15758977},
{"learn":[0.774513328],"iteration":824,"passed_time":136.6763653,"remaining_time":28.99195628},
{"learn":[0.7742007133],"iteration":825,"passed_time":136.8297151,"remaining_time":28.82369302},
{"learn":[0.7735718192],"iteration":826,"passed_time":137.0030751,"remaining_time":28.65965174},
{"learn":[0.7732615945],"iteration":827,"passed_time":137.1764694,"remaining_time":28.4955951},
{"learn":[0.7727560254],"iteration":828,"passed_time":137.3346609,"remaining_time":28.32837999},
{"learn":[0.7721959107],"iteration":829,"passed_time":137.4897311,"remaining_time":28.16054733},
{"learn":[0.771344426],"iteration":830,"passed_time":137.6653136,"remaining_time":27.99691697},
{"learn":[0.7709696176],"iteration":831,"passed_time":137.8290077,"remaining_time":27.83085733},
{"learn":[0.7702035894],"iteration":832,"passed_time":137.9932957,"remaining_time":27.66492242},
{"learn":[0.7699465825],"iteration":833,"passed_time":138.1510249,"remaining_time":27.49768601},
{"learn":[0.769361293],"iteration":834,"passed_time":138.3362458,"remaining_time":27.33590485},
{"learn":[0.768856255],"iteration":835,"passed_time":138.5055221,"remaining_time":27.17093975},
{"learn":[0.7684227584],"iteration":836,"passed_time":138.6683073,"remaining_time":27.00470023},
{"learn":[0.7680473658],"iteration":837,"passed_time":138.8255158,"remaining_time":26.83739088},
{"learn":[0.7677170649],"iteration":838,"passed_time":138.9801715,"remaining_time":26.66961575},
{"learn":[0.7673778944],"iteration":839,"passed_time":139.1450645,"remaining_time":26.50382181},
{"learn":[0.7671901981],"iteration":840,"passed_time":139.3028458,"remaining_time":26.33668547},
{"learn":[0.7667751842],"iteration":841,"passed_time":139.4680977,"remaining_time":26.17097321},
{"learn":[0.765754964],"iteration":842,"passed_time":139.6587593,"remaining_time":26.00999432},
{"learn":[0.7654660902],"iteration":843,"passed_time":139.8366776,"remaining_time":25.8465897},
{"learn":[0.7650334433],"iteration":844,"passed_time":140.0037096,"remaining_time":25.68115383},
{"learn":[0.7647085598],"iteration":845,"passed_time":140.1964331,"remaining_time":25.52039089},
{"learn":[0.7644874563],"iteration":846,"passed_time":140.3636454,"remaining_time":25.35494421},
{"learn":[0.7639477365],"iteration":847,"passed_time":140.5352764,"remaining_time":25.1902854},
{"learn":[0.763292499],"iteration":848,"passed_time":140.7054377,"remaining_time":25.02534876},
{"learn":[0.7623334102],"iteration":849,"passed_time":140.8916979,"remaining_time":24.8632408},
{"learn":[0.762102906],"iteration":850,"passed_time":141.0714125,"remaining_time":24.69993004},
{"learn":[0.7619971078],"iteration":851,"passed_time":141.2190879,"remaining_time":24.53101527},
{"learn":[0.7615132082],"iteration":852,"passed_time":141.3814819,"remaining_time":24.36468681},
{"learn":[0.7612268306],"iteration":853,"passed_time":141.5524113,"remaining_time":24.19982675},
{"learn":[0.7605837557],"iteration":854,"passed_time":141.7318174,"remaining_time":24.03639009},
{"learn":[0.7603426822],"iteration":855,"passed_time":141.8957412,"remaining_time":23.8703116},
{"learn":[0.7600984221],"iteration":856,"passed_time":142.0660581,"remaining_time":23.70530492},
{"learn":[0.7598235166],"iteration":857,"passed_time":142.2330653,"remaining_time":23.53973807},
{"learn":[0.7596233391],"iteration":858,"passed_time":142.3968909,"remaining_time":23.37364566},
{"learn":[0.7589688983],"iteration":859,"passed_time":142.579492,"remaining_time":23.21061498},
{"learn":[0.7588220448],"iteration":860,"passed_time":142.7228195,"remaining_time":23.0411985},
{"learn":[0.7586391816],"iteration":861,"passed_time":142.8711055,"remaining_time":22.87263638},
{"learn":[0.7581565037],"iteration":862,"passed_time":143.0489837,"remaining_time":22.70881896},
{"learn":[0.7577995939],"iteration":863,"passed_time":143.2358977,"remaining_time":22.5463913},
{"learn":[0.7575737104],"iteration":864,"passed_time":143.4013817,"remaining_time":22.38056246},
{"learn":[0.7570647953],"iteration":865,"passed_time":143.5652033,"remaining_time":22.21447718},
{"learn":[0.7565701141],"iteration":866,"passed_time":143.7177965,"remaining_time":22.04667467},
{"learn":[0.755593286],"iteration":867,"passed_time":143.8954894,"remaining_time":21.88272419},
{"learn":[0.75494968],"iteration":868,"passed_time":144.0520728,"remaining_time":21.71555988},
{"learn":[0.7544781554],"iteration":869,"passed_time":144.20454,"remaining_time":21.54780483},
{"learn":[0.7543093137],"iteration":870,"passed_time":144.3458461,"remaining_time":21.37843186},
{"learn":[0.7541237419],"iteration":871,"passed_time":144.5027938,"remaining_time":21.21141928},
{"learn":[0.753811977],"iteration":872,"passed_time":144.6666276,"remaining_time":21.0454315},
{"learn":[0.7535565634],"iteration":873,"passed_time":144.8257668,"remaining_time":20.87877188},
{"learn":[0.7529968736],"iteration":874,"passed_time":145.0039052,"remaining_time":20.71484361},
{"learn":[0.7523607032],"iteration":875,"passed_time":145.1836399,"remaining_time":20.55110884},
{"learn":[0.7520563739],"iteration":876,"passed_time":145.3432494,"remaining_time":20.38451503},
{"learn":[0.7515250457],"iteration":877,"passed_time":145.5120694,"remaining_time":20.21921693},
{"learn":[0.7509675335],"iteration":878,"passed_time":145.6884995,"remaining_time":20.05495841},
{"learn":[0.7508064461],"iteration":879,"passed_time":145.8487996,"remaining_time":19.88847268},
{"learn":[0.7505452434],"iteration":880,"passed_time":145.9997756,"remaining_time":19.72074154},
{"learn":[0.7504852273],"iteration":881,"passed_time":146.1392137,"remaining_time":19.55150478},
{"learn":[0.7501550858],"iteration":882,"passed_time":146.3071994,"remaining_time":19.38611815},
{"learn":[0.7489855689],"iteration":883,"passed_time":146.4986704,"remaining_time":19.22380743},
{"learn":[0.7481335531],"iteration":884,"passed_time":146.6815623,"remaining_time":19.06031601},
{"learn":[0.747627506],"iteration":885,"passed_time":146.8530627,"remaining_time":18.89531507},
{"learn":[0.7470945845],"iteration":886,"passed_time":147.0284617,"remaining_time":18.73079613},
{"learn":[0.7464258567],"iteration":887,"passed_time":147.2085862,"remaining_time":18.56684871},
{"learn":[0.7461492516],"iteration":888,"passed_time":147.3654208,"remaining_time":18.39995693},
{"learn":[0.7451794343],"iteration":889,"passed_time":147.5399135,"remaining_time":18.23527021},
{"learn":[0.7446352531],"iteration":890,"passed_time":147.7123905,"remaining_time":18.07031489},
{"learn":[0.7441729699],"iteration":891,"passed_time":147.8797119,"remaining_time":17.90471848},
{"learn":[0.7439465022],"iteration":892,"passed_time":148.0522357,"remaining_time":17.73974156},
{"learn":[0.7432411805],"iteration":893,"passed_time":148.246144,"remaining_time":17.57728329},
{"learn":[0.7427230771],"iteration":894,"passed_time":148.4209934,"remaining_time":17.41251878},
{"learn":[0.7425510487],"iteration":895,"passed_time":148.5663381,"remaining_time":17.2443071},
{"learn":[0.741921411],"iteration":896,"passed_time":148.7405989,"remaining_time":17.07946677},
{"learn":[0.7416849052],"iteration":897,"passed_time":148.9004904,"remaining_time":16.91297329},
{"learn":[0.7414109557],"iteration":898,"passed_time":149.0532914,"remaining_time":16.74569793},
{"learn":[0.7410200014],"iteration":899,"passed_time":149.208062,"remaining_time":16.57867356},
{"learn":[0.7406706335],"iteration":900,"passed_time":149.3621349,"remaining_time":16.41159972},
{"learn":[0.7396646472],"iteration":901,"passed_time":149.5414084,"remaining_time":16.24729271},
{"learn":[0.7395510946],"iteration":902,"passed_time":149.6871287,"remaining_time":16.07934827},
{"learn":[0.7385139849],"iteration":903,"passed_time":149.8690147,"remaining_time":15.9152936},
{"learn":[0.7381210124],"iteration":904,"passed_time":150.0152449,"remaining_time":15.74745665},
{"learn":[0.7379390521],"iteration":905,"passed_time":150.1734769,"remaining_time":15.58091261},
{"learn":[0.7375909589],"iteration":906,"passed_time":150.3335923,"remaining_time":15.41458003},
{"learn":[0.7372199745],"iteration":907,"passed_time":150.4836586,"remaining_time":15.24724294},
{"learn":[0.7364116695],"iteration":908,"passed_time":150.6514822,"remaining_time":15.08172154},
{"learn":[0.7360808375],"iteration":909,"passed_time":150.8065624,"remaining_time":14.91493475},
{"learn":[0.7356520147],"iteration":910,"passed_time":150.9927867,"remaining_time":14.75121627},
{"learn":[0.7350407536],"iteration":911,"passed_time":151.2142225,"remaining_time":14.59084603},
{"learn":[0.7346770455],"iteration":912,"passed_time":151.3894807,"remaining_time":14.42594176},
{"learn":[0.7342281465],"iteration":913,"passed_time":151.5595236,"remaining_time":14.2605241},
{"learn":[0.7339200463],"iteration":914,"passed_time":151.7226348,"remaining_time":14.09445241},
{"learn":[0.7329548496],"iteration":915,"passed_time":151.9126452,"remaining_time":13.93085393},
{"learn":[0.7324908138],"iteration":916,"passed_time":152.1276829,"remaining_time":13.76946312},
{"learn":[0.7322289738],"iteration":917,"passed_time":152.3060613,"remaining_time":13.60468085},
{"learn":[0.731928734],"iteration":918,"passed_time":152.4742254,"remaining_time":13.43896873},
{"learn":[0.7312229343],"iteration":919,"passed_time":152.6556789,"remaining_time":13.27440686},
{"learn":[0.7303502581],"iteration":920,"passed_time":152.8379811,"remaining_time":13.10988112},
{"learn":[0.7301939507],"iteration":921,"passed_time":153.0405637,"remaining_time":12.9470325},
{"learn":[0.7299588258],"iteration":922,"passed_time":153.2279606,"remaining_time":12.78283095},
{"learn":[0.7293746516],"iteration":923,"passed_time":153.4141128,"remaining_time":12.61847681},
{"learn":[0.7289766866],"iteration":924,"passed_time":153.5962602,"remaining_time":12.45375082},
{"learn":[0.7283733922],"iteration":925,"passed_time":153.7616455,"remaining_time":12.28764769},
{"learn":[0.7280256176],"iteration":926,"passed_time":153.9662857,"remaining_time":12.12463738},
{"learn":[0.7277340351],"iteration":927,"passed_time":154.1520448,"remaining_time":11.96007244},
{"learn":[0.7275119756],"iteration":928,"passed_time":154.3101242,"remaining_time":11.79334641},
{"learn":[0.727207965],"iteration":929,"passed_time":154.4756101,"remaining_time":11.62719646},
{"learn":[0.726278778],"iteration":930,"passed_time":154.6517437,"remaining_time":11.46183708},
{"learn":[0.7259100243],"iteration":931,"passed_time":154.8161399,"remaining_time":11.29559819},
{"learn":[0.7256804761],"iteration":932,"passed_time":154.9778516,"remaining_time":11.12917048},
{"learn":[0.7252177681],"iteration":933,"passed_time":155.1509658,"remaining_time":10.96355861},
{"learn":[0.7250249731],"iteration":934,"passed_time":155.3029985,"remaining_time":10.79646514},
{"learn":[0.7246419324],"iteration":935,"passed_time":155.4881957,"remaining_time":10.6316715},
{"learn":[0.7244658144],"iteration":936,"passed_time":155.6514507,"remaining_time":10.46535901},
{"learn":[0.7239259884],"iteration":937,"passed_time":155.8320049,"remaining_time":10.30019649},
{"learn":[0.7235205877],"iteration":938,"passed_time":155.9999292,"remaining_time":10.13418071},
{"learn":[0.723094208],"iteration":939,"passed_time":156.1718482,"remaining_time":9.968415845},
{"learn":[0.7226708026],"iteration":940,"passed_time":156.3412771,"remaining_time":9.802481773},
{"learn":[0.7223336503],"iteration":941,"passed_time":156.5065075,"remaining_time":9.636281777},
{"learn":[0.7218854948],"iteration":942,"passed_time":156.6834836,"remaining_time":9.470793813},
{"learn":[0.7215653914],"iteration":943,"passed_time":156.8484914,"remaining_time":9.304571523},
{"learn":[0.7212077912],"iteration":944,"passed_time":157.0281704,"remaining_time":9.139205683},
{"learn":[0.7210840412],"iteration":945,"passed_time":157.1737694,"remaining_time":8.971864214},
{"learn":[0.7204738954],"iteration":946,"passed_time":157.3671764,"remaining_time":8.807244298},
{"learn":[0.7202774357],"iteration":947,"passed_time":157.5318281,"remaining_time":8.64098635},
{"learn":[0.7198814358],"iteration":948,"passed_time":157.7148974,"remaining_time":8.475721568},
{"learn":[0.7196716451],"iteration":949,"passed_time":157.8844198,"remaining_time":8.309706304},
{"learn":[0.7194277037],"iteration":950,"passed_time":158.0430484,"remaining_time":8.143122367},
{"learn":[0.7190407859],"iteration":951,"passed_time":158.2205995,"remaining_time":7.977509218},
{"learn":[0.7187700231],"iteration":952,"passed_time":158.3885444,"remaining_time":7.81139726},
{"learn":[0.7184990478],"iteration":953,"passed_time":158.5538891,"remaining_time":7.645156079},
{"learn":[0.7178159268],"iteration":954,"passed_time":158.7477297,"remaining_time":7.480259516},
{"learn":[0.7169984865],"iteration":955,"passed_time":158.9365721,"remaining_time":7.315072357},
{"learn":[0.7167810478],"iteration":956,"passed_time":159.1109428,"remaining_time":7.149185516},
{"learn":[0.7167020708],"iteration":957,"passed_time":159.2612652,"remaining_time":6.982226658},
{"learn":[0.7164705575],"iteration":958,"passed_time":159.4207713,"remaining_time":6.815695123},
{"learn":[0.7162666622],"iteration":959,"passed_time":159.5962595,"remaining_time":6.649844144},
{"learn":[0.7158740614],"iteration":960,"passed_time":159.788942,"remaining_time":6.484670903},
{"learn":[0.7157160545],"iteration":961,"passed_time":159.9536563,"remaining_time":6.318335697},
{"learn":[0.7153351383],"iteration":962,"passed_time":160.1160181,"remaining_time":6.151913469},
{"learn":[0.7151461673],"iteration":963,"passed_time":160.2921483,"remaining_time":5.986013836},
{"learn":[0.7150362263],"iteration":964,"passed_time":160.4480611,"remaining_time":5.819359728},
{"learn":[0.7144751557],"iteration":965,"passed_time":160.6294286,"remaining_time":5.653623782},
{"learn":[0.7138921499],"iteration":966,"passed_time":160.8122601,"remaining_time":5.487905463},
{"learn":[0.7136002487],"iteration":967,"passed_time":160.9837821,"remaining_time":5.32177792},
{"learn":[0.713440914],"iteration":968,"passed_time":161.1421821,"remaining_time":5.155219449},
{"learn":[0.7132436576],"iteration":969,"passed_time":161.3104656,"remaining_time":4.988983474},
{"learn":[0.7129971137],"iteration":970,"passed_time":161.4665603,"remaining_time":4.822379248},
{"learn":[0.7126031321],"iteration":971,"passed_time":161.6488635,"remaining_time":4.656551625},
{"learn":[0.7122664047],"iteration":972,"passed_time":161.817225,"remaining_time":4.490303262},
{"learn":[0.711996651],"iteration":973,"passed_time":161.9875876,"remaining_time":4.32410398},
{"learn":[0.7114904977],"iteration":974,"passed_time":162.1494713,"remaining_time":4.157678751},
{"learn":[0.7109936389],"iteration":975,"passed_time":162.3338638,"remaining_time":3.991816323},
{"learn":[0.7109022339],"iteration":976,"passed_time":162.4920433,"remaining_time":3.825298871},
{"learn":[0.7102150233],"iteration":977,"passed_time":162.6666092,"remaining_time":3.659167078},
{"learn":[0.7095938303],"iteration":978,"passed_time":162.8506173,"remaining_time":3.493220595},
{"learn":[0.708656411],"iteration":979,"passed_time":163.0250965,"remaining_time":3.327042785},
{"learn":[0.7081119643],"iteration":980,"passed_time":163.1938739,"remaining_time":3.16073762},
{"learn":[0.7076555234],"iteration":981,"passed_time":163.3774041,"remaining_time":2.994697834},
{"learn":[0.7069457935],"iteration":982,"passed_time":163.5651261,"remaining_time":2.828694958},
{"learn":[0.706698984],"iteration":983,"passed_time":163.7277134,"remaining_time":2.662239242},
{"learn":[0.7065384277],"iteration":984,"passed_time":163.8860263,"remaining_time":2.495726289},
{"learn":[0.7063333639],"iteration":985,"passed_time":164.0469309,"remaining_time":2.329266768},
{"learn":[0.7062346826],"iteration":986,"passed_time":164.2035258,"remaining_time":2.162761738},
{"learn":[0.7057603432],"iteration":987,"passed_time":164.3855354,"remaining_time":1.99658545},
{"learn":[0.705181905],"iteration":988,"passed_time":164.5496612,"remaining_time":1.830178234},
{"learn":[0.7041811236],"iteration":989,"passed_time":164.7433387,"remaining_time":1.664074129},
{"learn":[0.7038529472],"iteration":990,"passed_time":164.9211141,"remaining_time":1.497769957},
{"learn":[0.7034794666],"iteration":991,"passed_time":165.0979521,"remaining_time":1.331435098},
{"learn":[0.7031896899],"iteration":992,"passed_time":165.2651511,"remaining_time":1.165011136},
{"learn":[0.7028215736],"iteration":993,"passed_time":165.4282391,"remaining_time":0.9985607996},
{"learn":[0.7024404449],"iteration":994,"passed_time":165.5922006,"remaining_time":0.8321216111},
{"learn":[0.7020995217],"iteration":995,"passed_time":165.7691796,"remaining_time":0.665739677},
{"learn":[0.7016997509],"iteration":996,"passed_time":165.9521811,"remaining_time":0.4993546073},
{"learn":[0.7015501887],"iteration":997,"passed_time":166.1254089,"remaining_time":0.3329166511},
{"learn":[0.7008890559],"iteration":998,"passed_time":166.2924587,"remaining_time":0.1664589176},
{"learn":[0.7007850103],"iteration":999,"passed_time":166.4387955,"remaining_time":0}
]}